{
 "BarTitle": {
  "   7   9   0": {
   "name": "BarTitle",
   "properties": {}
  }
 },
 "Break": {
  "   7   9   0": {
   "name": "Break",
   "properties": {}
  }
 },
 "Button": {
  "   7   9   0": {
   "name": "Button",
   "properties": {
    "ButtonFormType": {
     "name": "ButtonFormType",
     "mode": "plain",
     "value": "button"
    },
    "Disabled": {
     "name": "Disabled",
     "mode": "plain",
     "value": false
    },
    "IonColor": {
     "name": "IonColor",
     "mode": "plain",
     "value": false
    },
    "IonExpand": {
     "name": "IonExpand",
     "mode": "plain",
     "value": false
    },
    "IonShape": {
     "name": "IonShape",
     "mode": "plain",
     "value": false
    },
    "IonFill": {
     "name": "IonFill",
     "mode": "plain",
     "value": false
    },
    "IonSize": {
     "name": "IonSize",
     "mode": "plain",
     "value": false
    },
    "IonSlot": {
     "name": "IonSlot",
     "mode": "plain",
     "value": false
    },
    "IonMode": {
     "name": "IonMode",
     "mode": "plain",
     "value": false
    },
    "IonStrong": {
     "name": "IonStrong",
     "mode": "plain",
     "value": false
    },
    "LinkUrl": {
     "name": "LinkUrl",
     "mode": "plain",
     "value": false
    },
    "LinkDownload": {
     "name": "LinkDownload",
     "mode": "plain",
     "value": false
    },
    "LinkTarget": {
     "name": "LinkTarget",
     "mode": "plain",
     "value": false
    },
    "LinkRel": {
     "name": "LinkRel",
     "mode": "plain",
     "value": false
    },
    "LinkRouterDirection": {
     "name": "LinkRouterDirection",
     "mode": "plain",
     "value": false
    }
   }
  }
 },
 "ButtonSet": {
  "   7   9   0": {
   "name": "ButtonSet",
   "properties": {
    "SetPosition": {
     "name": "SetPosition",
     "mode": "plain",
     "value": false
    },
    "Collapse": {
     "name": "Collapse",
     "mode": "plain",
     "value": false
    }
   }
  }
 },
 "Content": {
  "   7   9   0": {
   "name": "Content",
   "properties": {
    "IonPadding": {
     "name": "IonPadding",
     "mode": "plain",
     "value": "padding"
    },
    "Fullscreen": {
     "name": "Fullscreen",
     "mode": "plain",
     "value": false
    }
   }
  }
 },
 "DivTag": {
  "   7   9   0": {
   "name": "DivTag",
   "properties": {}
  }
 },
 "Footer": {
  "   7   9   0": {
   "name": "Footer",
   "properties": {}
  }
 },
 "GenericItem": {
  "   7   9   0": {
   "name": "GenericItem",
   "properties": {
    "ItemPosition": {
     "name": "ItemPosition",
     "mode": "plain",
     "value": false
    }
   }
  }
 },
 "Header": {
  "   7   9   0": {
   "name": "Header",
   "properties": {
    "NoBorder": {
     "name": "NoBorder",
     "mode": "plain",
     "value": false
    }
   }
  }
 },
 "Heading": {
  "   7   9   0": {
   "name": "Heading",
   "properties": {
    "ionText": {
     "name": "ionText",
     "mode": "plain",
     "value": false
    },
    "IonColor": {
     "name": "IonColor",
     "mode": "plain",
     "value": false
    }
   }
  }
 },
 "Heading1": {
  "   7   9   0": {
   "name": "Heading1",
   "properties": {
    "ionText": {
     "name": "ionText",
     "mode": "plain",
     "value": false
    },
    "IonColor": {
     "name": "IonColor",
     "mode": "plain",
     "value": false
    }
   }
  }
 },
 "Heading2": {
  "   7   9   0": {
   "name": "Heading2",
   "properties": {
    "ionText": {
     "name": "ionText",
     "mode": "plain",
     "value": false
    },
    "IonColor": {
     "name": "IonColor",
     "mode": "plain",
     "value": false
    }
   }
  }
 },
 "Heading3": {
  "   7   9   0": {
   "name": "Heading3",
   "properties": {
    "ionText": {
     "name": "ionText",
     "mode": "plain",
     "value": false
    },
    "IonColor": {
     "name": "IonColor",
     "mode": "plain",
     "value": false
    }
   }
  }
 },
 "Heading4": {
  "   7   9   0": {
   "name": "Heading4",
   "properties": {
    "ionText": {
     "name": "ionText",
     "mode": "plain",
     "value": false
    },
    "IonColor": {
     "name": "IonColor",
     "mode": "plain",
     "value": false
    }
   }
  }
 },
 "Heading5": {
  "   7   9   0": {
   "name": "Heading5",
   "properties": {
    "ionText": {
     "name": "ionText",
     "mode": "plain",
     "value": false
    },
    "IonColor": {
     "name": "IonColor",
     "mode": "plain",
     "value": false
    }
   }
  }
 },
 "Heading6": {
  "   7   9   0": {
   "name": "Heading6",
   "properties": {
    "ionText": {
     "name": "ionText",
     "mode": "plain",
     "value": false
    },
    "IonColor": {
     "name": "IonColor",
     "mode": "plain",
     "value": false
    }
   }
  }
 },
 "Icon": {
  "   7   9   0": {
   "name": "Icon",
   "properties": {
    "IconName": {
     "name": "IconName",
     "mode": "plain",
     "value": "add"
    },
    "ItemPosition": {
     "name": "ItemPosition",
     "mode": "plain",
     "value": false
    },
    "IonColor": {
     "name": "IonColor",
     "mode": "plain",
     "value": false
    },
    "RangeLeft": {
     "name": "RangeLeft",
     "mode": "plain",
     "value": false
    },
    "RangeRight": {
     "name": "RangeRight",
     "mode": "plain",
     "value": false
    }
   }
  }
 },
 "Image": {
  "   7   9   0": {
   "name": "Image",
   "properties": {
    "url": {
     "name": "url",
     "mode": "script",
     "value": ""
    },
    "width": {
     "name": "width",
     "mode": "plain",
     "value": ""
    },
    "height": {
     "name": "height",
     "mode": "plain",
     "value": ""
    },
    "alt": {
     "name": "alt",
     "mode": "plain",
     "value": false
    }
   }
  }
 },
 "Label": {
  "   7   9   0": {
   "name": "Label",
   "properties": {
    "Fixed": {
     "name": "Fixed",
     "mode": "plain",
     "value": false
    },
    "Floating": {
     "name": "Floating",
     "mode": "plain",
     "value": false
    },
    "Stacked": {
     "name": "Stacked",
     "mode": "plain",
     "value": false
    },
    "RangeLeft": {
     "name": "RangeLeft",
     "mode": "plain",
     "value": false
    },
    "RangeRight": {
     "name": "RangeRight",
     "mode": "plain",
     "value": false
    }
   }
  }
 },
 "List": {
  "   7   9   0": {
   "name": "List",
   "properties": {
    "Nolines": {
     "name": "Nolines",
     "mode": "plain",
     "value": false
    },
    "Inset": {
     "name": "Inset",
     "mode": "plain",
     "value": false
    }
   }
  }
 },
 "ListItem": {
  "   7   9   0": {
   "name": "ListItem",
   "properties": {
    "ItemPosition": {
     "name": "ItemPosition",
     "mode": "plain",
     "value": false
    }
   }
  }
 },
 "Listdivider": {
  "   7   9   0": {
   "name": "Listdivider",
   "properties": {
    "IonColor": {
     "name": "IonColor",
     "mode": "plain",
     "value": false
    }
   }
  }
 },
 "Listgroup": {
  "   7   9   0": {
   "name": "Listgroup",
   "properties": {}
  }
 },
 "Listheader": {
  "   7   9   0": {
   "name": "Listheader",
   "properties": {}
  }
 },
 "Menu": {
  "   7   9   0": {
   "name": "Menu",
   "properties": {
    "MenuType": {
     "name": "MenuType",
     "mode": "plain",
     "value": false
    },
    "MenuSide": {
     "name": "MenuSide",
     "mode": "plain",
     "value": false
    },
    "MenuPersistent": {
     "name": "MenuPersistent",
     "mode": "plain",
     "value": false
    },
    "MenuSwipeEnabled": {
     "name": "MenuSwipeEnabled",
     "mode": "plain",
     "value": false
    }
   }
  }
 },
 "MenuAutoItems": {
  "   7   9   0": {
   "name": "MenuAutoItems",
   "properties": {}
  }
 },
 "MenuButton": {
  "   7   9   0": {
   "name": "MenuButton",
   "properties": {
    "ButtonFormType": {
     "name": "ButtonFormType",
     "mode": "plain",
     "value": "button"
    },
    "Disabled": {
     "name": "Disabled",
     "mode": "plain",
     "value": false
    },
    "IonColor": {
     "name": "IonColor",
     "mode": "plain",
     "value": false
    },
    "AutoHide": {
     "name": "AutoHide",
     "mode": "plain",
     "value": false
    },
    "MenuId": {
     "name": "MenuId",
     "mode": "plain",
     "value": false
    }
   }
  }
 },
 "MenuItem": {
  "   7   9   0": {
   "name": "MenuItem",
   "properties": {}
  }
 },
 "Paragraph": {
  "   7   9   0": {
   "name": "Paragraph",
   "properties": {}
  }
 },
 "ResetButton": {
  "   7   9   0": {
   "name": "ResetButton",
   "properties": {
    "ButtonFormType": {
     "name": "ButtonFormType",
     "mode": "plain",
     "value": "reset"
    },
    "Disabled": {
     "name": "Disabled",
     "mode": "plain",
     "value": false
    },
    "IonColor": {
     "name": "IonColor",
     "mode": "plain",
     "value": false
    },
    "IonExpand": {
     "name": "IonExpand",
     "mode": "plain",
     "value": false
    },
    "IonShape": {
     "name": "IonShape",
     "mode": "plain",
     "value": false
    },
    "IonFill": {
     "name": "IonFill",
     "mode": "plain",
     "value": false
    },
    "IonSize": {
     "name": "IonSize",
     "mode": "plain",
     "value": false
    },
    "IonSlot": {
     "name": "IonSlot",
     "mode": "plain",
     "value": false
    },
    "IonMode": {
     "name": "IonMode",
     "mode": "plain",
     "value": false
    },
    "IonStrong": {
     "name": "IonStrong",
     "mode": "plain",
     "value": false
    },
    "LinkUrl": {
     "name": "LinkUrl",
     "mode": "plain",
     "value": false
    },
    "LinkDownload": {
     "name": "LinkDownload",
     "mode": "plain",
     "value": false
    },
    "LinkTarget": {
     "name": "LinkTarget",
     "mode": "plain",
     "value": false
    },
    "LinkRel": {
     "name": "LinkRel",
     "mode": "plain",
     "value": false
    },
    "LinkRouterDirection": {
     "name": "LinkRouterDirection",
     "mode": "plain",
     "value": false
    }
   }
  }
 },
 "SpanTag": {
  "   7   9   0": {
   "name": "SpanTag",
   "properties": {}
  }
 },
 "SubmitButton": {
  "   7   9   0": {
   "name": "SubmitButton",
   "properties": {
    "ButtonFormType": {
     "name": "ButtonFormType",
     "mode": "plain",
     "value": "submit"
    },
    "Disabled": {
     "name": "Disabled",
     "mode": "plain",
     "value": false
    },
    "IonColor": {
     "name": "IonColor",
     "mode": "plain",
     "value": false
    },
    "IonExpand": {
     "name": "IonExpand",
     "mode": "plain",
     "value": false
    },
    "IonShape": {
     "name": "IonShape",
     "mode": "plain",
     "value": false
    },
    "IonFill": {
     "name": "IonFill",
     "mode": "plain",
     "value": false
    },
    "IonSize": {
     "name": "IonSize",
     "mode": "plain",
     "value": false
    },
    "IonSlot": {
     "name": "IonSlot",
     "mode": "plain",
     "value": false
    },
    "IonMode": {
     "name": "IonMode",
     "mode": "plain",
     "value": false
    },
    "IonStrong": {
     "name": "IonStrong",
     "mode": "plain",
     "value": false
    },
    "LinkUrl": {
     "name": "LinkUrl",
     "mode": "plain",
     "value": false
    },
    "LinkDownload": {
     "name": "LinkDownload",
     "mode": "plain",
     "value": false
    },
    "LinkTarget": {
     "name": "LinkTarget",
     "mode": "plain",
     "value": false
    },
    "LinkRel": {
     "name": "LinkRel",
     "mode": "plain",
     "value": false
    },
    "LinkRouterDirection": {
     "name": "LinkRouterDirection",
     "mode": "plain",
     "value": false
    },
    "AutoDisable": {
     "name": "AutoDisable",
     "mode": "plain",
     "value": "true"
    }
   }
  }
 },
 "ToolBar": {
  "   7   9   0": {
   "name": "ToolBar",
   "properties": {
    "IonColor": {
     "name": "IonColor",
     "mode": "plain",
     "value": false
    },
    "BarMode": {
     "name": "BarMode",
     "mode": "plain",
     "value": false
    }
   }
  }
 }
}