{
 "BarTitle": {
  "   7   9   0": {
   "name": "BarTitle",
   "properties": {}
  }
 },
 "Break": {
  "   7   9   0": {
   "name": "Break",
   "properties": {}
  }
 },
 "Button": {
  "   7   9   0": {
   "name": "Button",
   "properties": {
    "ButtonFormType": {
     "name": "ButtonFormType",
     "mode": "plain",
     "value": "button"
    },
    "Disabled": {
     "name": "Disabled",
     "mode": "plain",
     "value": "false"
    },
    "IonColor": {
     "name": "IonColor",
     "mode": "plain",
     "value": false
    },
    "IonExpand": {
     "name": "IonExpand",
     "mode": "plain",
     "value": false
    },
    "IonShape": {
     "name": "IonShape",
     "mode": "plain",
     "value": false
    },
    "IonFill": {
     "name": "IonFill",
     "mode": "plain",
     "value": false
    },
    "IonSize": {
     "name": "IonSize",
     "mode": "plain",
     "value": false
    },
    "IconSlot": {
     "name": "IconSlot",
     "mode": "plain",
     "value": false
    },
    "IonMode": {
     "name": "IonMode",
     "mode": "plain",
     "value": false
    },
    "IonStrong": {
     "name": "IonStrong",
     "mode": "plain",
     "value": false
    },
    "LinkUrl": {
     "name": "LinkUrl",
     "mode": "plain",
     "value": false
    },
    "LinkDownload": {
     "name": "LinkDownload",
     "mode": "plain",
     "value": false
    },
    "LinkTarget": {
     "name": "LinkTarget",
     "mode": "plain",
     "value": false
    },
    "LinkRel": {
     "name": "LinkRel",
     "mode": "plain",
     "value": false
    },
    "LinkRouterPath": {
     "name": "LinkRouterPath",
     "mode": "plain",
     "value": false
    },
    "LinkRouterDirection": {
     "name": "LinkRouterDirection",
     "mode": "plain",
     "value": false
    }
   }
  }
 },
 "ButtonSet": {
  "   7   9   0": {
   "name": "ButtonSet",
   "properties": {
    "SetPosition": {
     "name": "SetPosition",
     "mode": "plain",
     "value": false
    },
    "Collapse": {
     "name": "Collapse",
     "mode": "plain",
     "value": "false"
    }
   }
  }
 },
 "Content": {
  "   7   9   0": {
   "name": "Content",
   "properties": {
    "IonColor": {
     "name": "IonColor",
     "mode": "plain",
     "value": false
    },
    "IonSlot": {
     "name": "IonSlot",
     "mode": "plain",
     "value": false
    },
    "Fullscreen": {
     "name": "Fullscreen",
     "mode": "plain",
     "value": "false"
    },
    "ForceOverScroll": {
     "name": "ForceOverScroll",
     "mode": "plain",
     "value": "false"
    },
    "ScrollEvents": {
     "name": "ScrollEvents",
     "mode": "plain",
     "value": "false"
    },
    "ScrollX": {
     "name": "ScrollX",
     "mode": "plain",
     "value": "false"
    },
    "ScrollY": {
     "name": "ScrollY",
     "mode": "plain",
     "value": "false"
    }
   }
  }
 },
 "DivTag": {
  "   7   9   0": {
   "name": "DivTag",
   "properties": {}
  }
 },
 "Footer": {
  "   7   9   0": {
   "name": "Footer",
   "properties": {
    "IonMode": {
     "name": "IonMode",
     "mode": "plain",
     "value": false
    },
    "Translucent": {
     "name": "Translucent",
     "mode": "plain",
     "value": "false"
    }
   }
  }
 },
 "GenericItem": {
  "   7   9   0": {
   "name": "GenericItem",
   "properties": {
    "Button": {
     "name": "Button",
     "mode": "plain",
     "value": "false"
    },
    "Lines": {
     "name": "Lines",
     "mode": "plain",
     "value": false
    },
    "Detail": {
     "name": "Detail",
     "mode": "plain",
     "value": "false"
    },
    "DetailIconName": {
     "name": "DetailIconName",
     "mode": "plain",
     "value": "chevron-forward"
    },
    "ButtonFormType": {
     "name": "ButtonFormType",
     "mode": "plain",
     "value": "button"
    },
    "Disabled": {
     "name": "Disabled",
     "mode": "plain",
     "value": "false"
    },
    "IonColor": {
     "name": "IonColor",
     "mode": "plain",
     "value": false
    },
    "IonSlot": {
     "name": "IonSlot",
     "mode": "plain",
     "value": false
    },
    "IonMode": {
     "name": "IonMode",
     "mode": "plain",
     "value": false
    },
    "LinkUrl": {
     "name": "LinkUrl",
     "mode": "plain",
     "value": false
    },
    "LinkDownload": {
     "name": "LinkDownload",
     "mode": "plain",
     "value": false
    },
    "LinkTarget": {
     "name": "LinkTarget",
     "mode": "plain",
     "value": false
    },
    "LinkRel": {
     "name": "LinkRel",
     "mode": "plain",
     "value": false
    },
    "LinkRouterPath": {
     "name": "LinkRouterPath",
     "mode": "plain",
     "value": false
    },
    "LinkRouterDirection": {
     "name": "LinkRouterDirection",
     "mode": "plain",
     "value": false
    }
   }
  }
 },
 "Header": {
  "   7   9   0": {
   "name": "Header",
   "properties": {
    "IonMode": {
     "name": "IonMode",
     "mode": "plain",
     "value": false
    },
    "Collapse": {
     "name": "Collapse",
     "mode": "plain",
     "value": false
    },
    "Translucent": {
     "name": "Translucent",
     "mode": "plain",
     "value": "false"
    }
   }
  }
 },
 "Heading": {
  "   7   9   0": {
   "name": "Heading",
   "properties": {}
  }
 },
 "Heading1": {
  "   7   9   0": {
   "name": "Heading1",
   "properties": {}
  }
 },
 "Heading2": {
  "   7   9   0": {
   "name": "Heading2",
   "properties": {}
  }
 },
 "Heading3": {
  "   7   9   0": {
   "name": "Heading3",
   "properties": {}
  }
 },
 "Heading4": {
  "   7   9   0": {
   "name": "Heading4",
   "properties": {}
  }
 },
 "Heading5": {
  "   7   9   0": {
   "name": "Heading5",
   "properties": {}
  }
 },
 "Heading6": {
  "   7   9   0": {
   "name": "Heading6",
   "properties": {}
  }
 },
 "Icon": {
  "   7   9   0": {
   "name": "Icon",
   "properties": {
    "IconName": {
     "name": "IconName",
     "mode": "plain",
     "value": "add"
    },
    "IconMdName": {
     "name": "IconMdName",
     "mode": "plain",
     "value": false
    },
    "IconIosName": {
     "name": "IconIosName",
     "mode": "plain",
     "value": false
    },
    "IonSize": {
     "name": "IonSize",
     "mode": "plain",
     "value": false
    },
    "IconSlot": {
     "name": "IconSlot",
     "mode": "plain",
     "value": false
    },
    "IconSource": {
     "name": "IconSource",
     "mode": "plain",
     "value": false
    }
   }
  }
 },
 "Image": {
  "   7   9   0": {
   "name": "Image",
   "properties": {
    "url": {
     "name": "url",
     "mode": "script",
     "value": ""
    },
    "width": {
     "name": "width",
     "mode": "plain",
     "value": ""
    },
    "height": {
     "name": "height",
     "mode": "plain",
     "value": ""
    },
    "alt": {
     "name": "alt",
     "mode": "plain",
     "value": false
    }
   }
  }
 },
 "Label": {
  "   7   9   0": {
   "name": "Label",
   "properties": {
    "IonColor": {
     "name": "IonColor",
     "mode": "plain",
     "value": false
    },
    "IonMode": {
     "name": "IonMode",
     "mode": "plain",
     "value": false
    },
    "Position": {
     "name": "Position",
     "mode": "plain",
     "value": false
    }
   }
  }
 },
 "List": {
  "   7   9   0": {
   "name": "List",
   "properties": {
    "IonMode": {
     "name": "IonMode",
     "mode": "plain",
     "value": false
    },
    "Inset": {
     "name": "Inset",
     "mode": "plain",
     "value": "false"
    },
    "Lines": {
     "name": "Lines",
     "mode": "plain",
     "value": false
    }
   }
  }
 },
 "ListItem": {
  "   7   9   0": {
   "name": "ListItem",
   "properties": {
    "Button": {
     "name": "Button",
     "mode": "plain",
     "value": "false"
    },
    "Lines": {
     "name": "Lines",
     "mode": "plain",
     "value": false
    },
    "Detail": {
     "name": "Detail",
     "mode": "plain",
     "value": "false"
    },
    "DetailIconName": {
     "name": "DetailIconName",
     "mode": "plain",
     "value": "chevron-forward"
    },
    "ButtonFormType": {
     "name": "ButtonFormType",
     "mode": "plain",
     "value": "button"
    },
    "Disabled": {
     "name": "Disabled",
     "mode": "plain",
     "value": "false"
    },
    "IonColor": {
     "name": "IonColor",
     "mode": "plain",
     "value": false
    },
    "IonSlot": {
     "name": "IonSlot",
     "mode": "plain",
     "value": false
    },
    "IonMode": {
     "name": "IonMode",
     "mode": "plain",
     "value": false
    },
    "LinkUrl": {
     "name": "LinkUrl",
     "mode": "plain",
     "value": false
    },
    "LinkDownload": {
     "name": "LinkDownload",
     "mode": "plain",
     "value": false
    },
    "LinkTarget": {
     "name": "LinkTarget",
     "mode": "plain",
     "value": false
    },
    "LinkRel": {
     "name": "LinkRel",
     "mode": "plain",
     "value": false
    },
    "LinkRouterPath": {
     "name": "LinkRouterPath",
     "mode": "plain",
     "value": false
    },
    "LinkRouterDirection": {
     "name": "LinkRouterDirection",
     "mode": "plain",
     "value": false
    }
   }
  }
 },
 "Listdivider": {
  "   7   9   0": {
   "name": "Listdivider",
   "properties": {
    "IonColor": {
     "name": "IonColor",
     "mode": "plain",
     "value": false
    },
    "IonMode": {
     "name": "IonMode",
     "mode": "plain",
     "value": false
    },
    "Sticky": {
     "name": "Sticky",
     "mode": "plain",
     "value": "false"
    }
   }
  }
 },
 "Listgroup": {
  "   7   9   0": {
   "name": "Listgroup",
   "properties": {}
  }
 },
 "Listheader": {
  "   7   9   0": {
   "name": "Listheader",
   "properties": {
    "IonMode": {
     "name": "IonMode",
     "mode": "plain",
     "value": false
    },
    "IonColor": {
     "name": "IonColor",
     "mode": "plain",
     "value": false
    },
    "Lines": {
     "name": "Lines",
     "mode": "plain",
     "value": false
    }
   }
  }
 },
 "Menu": {
  "   7   9   0": {
   "name": "Menu",
   "properties": {
    "Disabled": {
     "name": "Disabled",
     "mode": "plain",
     "value": "false"
    },
    "MenuType": {
     "name": "MenuType",
     "mode": "plain",
     "value": false
    },
    "MenuSide": {
     "name": "MenuSide",
     "mode": "plain",
     "value": "start"
    },
    "MenuSwipeEnabled": {
     "name": "MenuSwipeEnabled",
     "mode": "plain",
     "value": "true"
    },
    "MenuMaxEdgeStart": {
     "name": "MenuMaxEdgeStart",
     "mode": "plain",
     "value": false
    }
   }
  }
 },
 "MenuAutoItems": {
  "   7   9   0": {
   "name": "MenuAutoItems",
   "properties": {}
  }
 },
 "MenuButton": {
  "   7   9   0": {
   "name": "MenuButton",
   "properties": {
    "ButtonFormType": {
     "name": "ButtonFormType",
     "mode": "plain",
     "value": "button"
    },
    "Disabled": {
     "name": "Disabled",
     "mode": "plain",
     "value": "false"
    },
    "IonColor": {
     "name": "IonColor",
     "mode": "plain",
     "value": false
    },
    "AutoHide": {
     "name": "AutoHide",
     "mode": "plain",
     "value": "true"
    },
    "MenuId": {
     "name": "MenuId",
     "mode": "plain",
     "value": false
    }
   }
  }
 },
 "MenuItem": {
  "   7   9   0": {
   "name": "MenuItem",
   "properties": {}
  }
 },
 "Paragraph": {
  "   7   9   0": {
   "name": "Paragraph",
   "properties": {}
  }
 },
 "ResetButton": {
  "   7   9   0": {
   "name": "ResetButton",
   "properties": {
    "ButtonFormType": {
     "name": "ButtonFormType",
     "mode": "plain",
     "value": "reset"
    },
    "Disabled": {
     "name": "Disabled",
     "mode": "plain",
     "value": "false"
    },
    "IonColor": {
     "name": "IonColor",
     "mode": "plain",
     "value": false
    },
    "IonExpand": {
     "name": "IonExpand",
     "mode": "plain",
     "value": false
    },
    "IonShape": {
     "name": "IonShape",
     "mode": "plain",
     "value": false
    },
    "IonFill": {
     "name": "IonFill",
     "mode": "plain",
     "value": false
    },
    "IonSize": {
     "name": "IonSize",
     "mode": "plain",
     "value": false
    },
    "IconSlot": {
     "name": "IconSlot",
     "mode": "plain",
     "value": false
    },
    "IonMode": {
     "name": "IonMode",
     "mode": "plain",
     "value": false
    },
    "IonStrong": {
     "name": "IonStrong",
     "mode": "plain",
     "value": false
    },
    "LinkUrl": {
     "name": "LinkUrl",
     "mode": "plain",
     "value": false
    },
    "LinkDownload": {
     "name": "LinkDownload",
     "mode": "plain",
     "value": false
    },
    "LinkTarget": {
     "name": "LinkTarget",
     "mode": "plain",
     "value": false
    },
    "LinkRel": {
     "name": "LinkRel",
     "mode": "plain",
     "value": false
    },
    "LinkRouterPath": {
     "name": "LinkRouterPath",
     "mode": "plain",
     "value": false
    },
    "LinkRouterDirection": {
     "name": "LinkRouterDirection",
     "mode": "plain",
     "value": false
    }
   }
  }
 },
 "SpanTag": {
  "   7   9   0": {
   "name": "SpanTag",
   "properties": {}
  }
 },
 "SubmitButton": {
  "   7   9   0": {
   "name": "SubmitButton",
   "properties": {
    "ButtonFormType": {
     "name": "ButtonFormType",
     "mode": "plain",
     "value": "submit"
    },
    "Disabled": {
     "name": "Disabled",
     "mode": "plain",
     "value": "false"
    },
    "IonColor": {
     "name": "IonColor",
     "mode": "plain",
     "value": false
    },
    "IonExpand": {
     "name": "IonExpand",
     "mode": "plain",
     "value": false
    },
    "IonShape": {
     "name": "IonShape",
     "mode": "plain",
     "value": false
    },
    "IonFill": {
     "name": "IonFill",
     "mode": "plain",
     "value": false
    },
    "IonSize": {
     "name": "IonSize",
     "mode": "plain",
     "value": false
    },
    "IconSlot": {
     "name": "IconSlot",
     "mode": "plain",
     "value": false
    },
    "IonMode": {
     "name": "IonMode",
     "mode": "plain",
     "value": false
    },
    "IonStrong": {
     "name": "IonStrong",
     "mode": "plain",
     "value": false
    },
    "LinkUrl": {
     "name": "LinkUrl",
     "mode": "plain",
     "value": false
    },
    "LinkDownload": {
     "name": "LinkDownload",
     "mode": "plain",
     "value": false
    },
    "LinkTarget": {
     "name": "LinkTarget",
     "mode": "plain",
     "value": false
    },
    "LinkRel": {
     "name": "LinkRel",
     "mode": "plain",
     "value": false
    },
    "LinkRouterPath": {
     "name": "LinkRouterPath",
     "mode": "plain",
     "value": false
    },
    "LinkRouterDirection": {
     "name": "LinkRouterDirection",
     "mode": "plain",
     "value": false
    },
    "AutoDisable": {
     "name": "AutoDisable",
     "mode": "plain",
     "value": "true"
    }
   }
  }
 },
 "ToolBar": {
  "   7   9   0": {
   "name": "ToolBar",
   "properties": {
    "IonColor": {
     "name": "IonColor",
     "mode": "plain",
     "value": false
    },
    "BarMode": {
     "name": "BarMode",
     "mode": "plain",
     "value": false
    },
    "BarSlot": {
     "name": "BarSlot",
     "mode": "plain",
     "value": false
    }
   }
  }
 },
 "TextItem": {
  "   7   9   0": {
   "name": "TextItem",
   "properties": {
    "IonColor": {
     "name": "IonColor",
     "mode": "plain",
     "value": false
    },
    "IonMode": {
     "name": "IonMode",
     "mode": "plain",
     "value": false
    }
   }
  }
 },
 "MenuToggle": {
  "   7   9   0": {
   "name": "MenuToggle",
   "properties": {
    "AutoHide": {
     "name": "AutoHide",
     "mode": "plain",
     "value": "true"
    },
    "MenuId": {
     "name": "MenuId",
     "mode": "plain",
     "value": false
    }
   }
  }
 },
 "BackButton": {
  "   7   9   0": {
   "name": "BackButton",
   "properties": {
    "ButtonFormType": {
     "name": "ButtonFormType",
     "mode": "plain",
     "value": "button"
    },
    "Disabled": {
     "name": "Disabled",
     "mode": "plain",
     "value": "false"
    },
    "IonColor": {
     "name": "IonColor",
     "mode": "plain",
     "value": false
    },
    "IonIcon": {
     "name": "IonIcon",
     "mode": "plain",
     "value": false
    },
    "IonMode": {
     "name": "IonMode",
     "mode": "plain",
     "value": false
    },
    "ButtonText": {
     "name": "ButtonText",
     "mode": "plain",
     "value": false
    },
    "DefaultHref": {
     "name": "DefaultHref",
     "mode": "plain",
     "value": "\/"
    }
   }
  }
 },
 "Searchbar": {
  "   7   9   0": {
   "name": "Searchbar",
   "properties": {
    "Disabled": {
     "name": "Disabled",
     "mode": "plain",
     "value": false
    },
    "IonColor": {
     "name": "IonColor",
     "mode": "plain",
     "value": false
    },
    "IonMode": {
     "name": "IonMode",
     "mode": "plain",
     "value": false
    },
    "animated": {
     "name": "animated",
     "mode": "plain",
     "value": "false"
    },
    "autocomplete": {
     "name": "autocomplete",
     "mode": "plain",
     "value": "off"
    },
    "autocorrect": {
     "name": "autocorrect",
     "mode": "plain",
     "value": "off"
    },
    "cancelButtonIcon": {
     "name": "cancelButtonIcon",
     "mode": "plain",
     "value": "arrow-back-sharp"
    },
    "cancelButtonText": {
     "name": "cancelButtonText",
     "mode": "plain",
     "value": "Cancel"
    },
    "clearIcon": {
     "name": "clearIcon",
     "mode": "plain",
     "value": false
    },
    "searchIcon": {
     "name": "searchIcon",
     "mode": "plain",
     "value": false
    },
    "debounce": {
     "name": "debounce",
     "mode": "plain",
     "value": "250"
    },
    "enterkeyhint": {
     "name": "enterkeyhint",
     "mode": "plain",
     "value": false
    },
    "inputmode": {
     "name": "inputmode",
     "mode": "plain",
     "value": false
    },
    "placeholder": {
     "name": "placeholder",
     "mode": "plain",
     "value": "Search"
    },
    "showCancelButton": {
     "name": "showCancelButton",
     "mode": "plain",
     "value": "never"
    },
    "spellcheck": {
     "name": "spellcheck",
     "mode": "plain",
     "value": "false"
    },
    "type": {
     "name": "type",
     "mode": "plain",
     "value": "search"
    },
    "value": {
     "name": "value",
     "mode": "plain",
     "value": ""
    }
   }
  }
 },
 "Input": {
  "   7   9   0": {
   "name": "Input",
   "properties": {
    "ControlName": {
     "name": "ControlName",
     "mode": "plain",
     "value": ""
    },
    "DoubleBinding": {
     "name": "DoubleBinding",
     "mode": "script",
     "value": false
    },
    "Disabled": {
     "name": "Disabled",
     "mode": "plain",
     "value": "false"
    },
    "IonColor": {
     "name": "IonColor",
     "mode": "plain",
     "value": false
    },
    "IonMode": {
     "name": "IonMode",
     "mode": "plain",
     "value": false
    },
    "Accept": {
     "name": "Accept",
     "mode": "plain",
     "value": false
    },
    "Autocapitalize": {
     "name": "Autocapitalize",
     "mode": "plain",
     "value": "off"
    },
    "AutoComplete": {
     "name": "AutoComplete",
     "mode": "plain",
     "value": "off"
    },
    "AutoCorrect": {
     "name": "AutoCorrect",
     "mode": "plain",
     "value": "off"
    },
    "AutoFocus": {
     "name": "AutoFocus",
     "mode": "plain",
     "value": "false"
    },
    "ClearInput": {
     "name": "ClearInput",
     "mode": "plain",
     "value": "false"
    },
    "ClearOnEdit": {
     "name": "ClearOnEdit",
     "mode": "plain",
     "value": "false"
    },
    "Debounce": {
     "name": "Debounce",
     "mode": "plain",
     "value": 0
    },
    "EnterKeyHint": {
     "name": "EnterKeyHint",
     "mode": "plain",
     "value": false
    },
    "InputMode": {
     "name": "InputMode",
     "mode": "plain",
     "value": false
    },
    "Max": {
     "name": "Max",
     "mode": "plain",
     "value": false
    },
    "MaxLength": {
     "name": "MaxLength",
     "mode": "plain",
     "value": false
    },
    "Min": {
     "name": "Min",
     "mode": "plain",
     "value": false
    },
    "MinLength": {
     "name": "MinLength",
     "mode": "plain",
     "value": false
    },
    "Multiple": {
     "name": "Multiple",
     "mode": "plain",
     "value": "false"
    },
    "Pattern": {
     "name": "Pattern",
     "mode": "plain",
     "value": false
    },
    "Placeholder": {
     "name": "Placeholder",
     "mode": "plain",
     "value": false
    },
    "Readonly": {
     "name": "Readonly",
     "mode": "plain",
     "value": "false"
    },
    "Required": {
     "name": "Required",
     "mode": "plain",
     "value": "false"
    },
    "Size": {
     "name": "Size",
     "mode": "plain",
     "value": false
    },
    "Spellcheck": {
     "name": "Spellcheck",
     "mode": "plain",
     "value": "false"
    },
    "Step": {
     "name": "Step",
     "mode": "plain",
     "value": false
    },
    "Type": {
     "name": "Type",
     "mode": "plain",
     "value": "text"
    },
    "Value": {
     "name": "Value",
     "mode": "plain",
     "value": ""
    }
   }
  }
 },
 "CheckBox": {
  "   7   9   0": {
   "name": "CheckBox",
   "properties": {
    "ControlName": {
     "name": "ControlName",
     "mode": "plain",
     "value": ""
    },
    "DoubleBinding": {
     "name": "DoubleBinding",
     "mode": "script",
     "value": false
    },
    "Disabled": {
     "name": "Disabled",
     "mode": "plain",
     "value": "false"
    },
    "IonColor": {
     "name": "IonColor",
     "mode": "plain",
     "value": false
    },
    "IonMode": {
     "name": "IonMode",
     "mode": "plain",
     "value": false
    },
    "Checked": {
     "name": "Checked",
     "mode": "plain",
     "value": "false"
    },
    "Indeterminate": {
     "name": "Indeterminate",
     "mode": "plain",
     "value": "false"
    },
    "Value": {
     "name": "Value",
     "mode": "plain",
     "value": false
    }
   }
  }
 },
 "Select": {
  "   7   9   0": {
   "name": "Select",
   "properties": {
    "ControlName": {
     "name": "ControlName",
     "mode": "plain",
     "value": ""
    },
    "IonMode": {
     "name": "IonMode",
     "mode": "plain",
     "value": false
    },
    "Disabled": {
     "name": "Disabled",
     "mode": "plain",
     "value": "false"
    },
    "DoubleBinding": {
     "name": "DoubleBinding",
     "mode": "script",
     "value": false
    },
    "CancelText": {
     "name": "CancelText",
     "mode": "plain",
     "value": "Cancel"
    },
    "OkText": {
     "name": "OkText",
     "mode": "plain",
     "value": "Ok"
    },
    "CompareWith": {
     "name": "CompareWith",
     "mode": "plain",
     "value": false
    },
    "Interface": {
     "name": "Interface",
     "mode": "plain",
     "value": false
    },
    "InterfaceOptions": {
     "name": "InterfaceOptions",
     "mode": "plain",
     "value": false
    },
    "Placeholder": {
     "name": "Placeholder",
     "mode": "plain",
     "value": false
    },
    "SelectedText": {
     "name": "SelectedText",
     "mode": "plain",
     "value": false
    },
    "Multiple": {
     "name": "Multiple",
     "mode": "plain",
     "value": "false"
    },
    "Value": {
     "name": "Value",
     "mode": "plain",
     "value": false
    }
   }
  }
 },
 "SelectOption": {
  "   7   9   0": {
   "name": "SelectOption",
   "properties": {
    "Disabled": {
     "name": "Disabled",
     "mode": "plain",
     "value": "false"
    },
    "Value": {
     "name": "Value",
     "mode": "plain",
     "value": false
    }
   }
  }
 },
 "Toggle": {
  "   7   9   0": {
   "name": "Toggle",
   "properties": {
    "ControlName": {
     "name": "ControlName",
     "mode": "plain",
     "value": ""
    },
    "DoubleBinding": {
     "name": "DoubleBinding",
     "mode": "script",
     "value": false
    },
    "Disabled": {
     "name": "Disabled",
     "mode": "plain",
     "value": "false"
    },
    "IonColor": {
     "name": "IonColor",
     "mode": "plain",
     "value": false
    },
    "IonMode": {
     "name": "IonMode",
     "mode": "plain",
     "value": false
    },
    "Checked": {
     "name": "Checked",
     "mode": "plain",
     "value": "false"
    },
    "Value": {
     "name": "Value",
     "mode": "plain",
     "value": false
    }
   }
  }
 },
 "RadioButton": {
  "   7   9   0": {
   "name": "RadioButton",
   "properties": {
    "Disabled": {
     "name": "Disabled",
     "mode": "plain",
     "value": "false"
    },
    "IonColor": {
     "name": "IonColor",
     "mode": "plain",
     "value": false
    },
    "IonMode": {
     "name": "IonMode",
     "mode": "plain",
     "value": false
    },
    "IonSlot": {
     "name": "IonSlot",
     "mode": "plain",
     "value": false
    },
    "Value": {
     "name": "Value",
     "mode": "plain",
     "value": ""
    }
   }
  }
 },
 "RadioGroup": {
  "   7   9   0": {
   "name": "RadioGroup",
   "properties": {
    "ControlName": {
     "name": "ControlName",
     "mode": "plain",
     "value": ""
    },
    "DoubleBinding": {
     "name": "DoubleBinding",
     "mode": "script",
     "value": false
    },
    "AllowEmptySelection": {
     "name": "AllowEmptySelection",
     "mode": "plain",
     "value": "false"
    },
    "Value": {
     "name": "Value",
     "mode": "plain",
     "value": ""
    }
   }
  }
 },
 "FormItem": {
  "   7   9   0": {
   "name": "FormItem",
   "properties": {
    "Button": {
     "name": "Button",
     "mode": "plain",
     "value": "false"
    },
    "Lines": {
     "name": "Lines",
     "mode": "plain",
     "value": false
    },
    "Detail": {
     "name": "Detail",
     "mode": "plain",
     "value": "false"
    },
    "DetailIconName": {
     "name": "DetailIconName",
     "mode": "plain",
     "value": "chevron-forward"
    },
    "ButtonFormType": {
     "name": "ButtonFormType",
     "mode": "plain",
     "value": "button"
    },
    "Disabled": {
     "name": "Disabled",
     "mode": "plain",
     "value": "false"
    },
    "IonColor": {
     "name": "IonColor",
     "mode": "plain",
     "value": false
    },
    "IonSlot": {
     "name": "IonSlot",
     "mode": "plain",
     "value": false
    },
    "IonMode": {
     "name": "IonMode",
     "mode": "plain",
     "value": false
    },
    "LinkUrl": {
     "name": "LinkUrl",
     "mode": "plain",
     "value": false
    },
    "LinkDownload": {
     "name": "LinkDownload",
     "mode": "plain",
     "value": false
    },
    "LinkTarget": {
     "name": "LinkTarget",
     "mode": "plain",
     "value": false
    },
    "LinkRel": {
     "name": "LinkRel",
     "mode": "plain",
     "value": false
    },
    "LinkRouterPath": {
     "name": "LinkRouterPath",
     "mode": "plain",
     "value": false
    },
    "LinkRouterDirection": {
     "name": "LinkRouterDirection",
     "mode": "plain",
     "value": false
    }
   }
  }
 },
 "TextArea": {
  "   7   9   0": {
   "name": "TextArea",
   "properties": {
    "ControlName": {
     "name": "ControlName",
     "mode": "plain",
     "value": ""
    },
    "DoubleBinding": {
     "name": "DoubleBinding",
     "mode": "script",
     "value": false
    },
    "Disabled": {
     "name": "Disabled",
     "mode": "plain",
     "value": "false"
    },
    "IonColor": {
     "name": "IonColor",
     "mode": "plain",
     "value": false
    },
    "IonMode": {
     "name": "IonMode",
     "mode": "plain",
     "value": false
    },
    "AutoGrow": {
     "name": "AutoGrow",
     "mode": "plain",
     "value": "false"
    },
    "Autocapitalize": {
     "name": "Autocapitalize",
     "mode": "plain",
     "value": "off"
    },
    "AutoFocus": {
     "name": "AutoFocus",
     "mode": "plain",
     "value": "false"
    },
    "ClearOnEdit": {
     "name": "ClearOnEdit",
     "mode": "plain",
     "value": "false"
    },
    "Debounce": {
     "name": "Debounce",
     "mode": "plain",
     "value": 0
    },
    "EnterKeyHint": {
     "name": "EnterKeyHint",
     "mode": "plain",
     "value": false
    },
    "InputMode": {
     "name": "InputMode",
     "mode": "plain",
     "value": false
    },
    "MaxLength": {
     "name": "MaxLength",
     "mode": "plain",
     "value": false
    },
    "MinLength": {
     "name": "MinLength",
     "mode": "plain",
     "value": false
    },
    "Placeholder": {
     "name": "Placeholder",
     "mode": "plain",
     "value": false
    },
    "Readonly": {
     "name": "Readonly",
     "mode": "plain",
     "value": "false"
    },
    "Required": {
     "name": "Required",
     "mode": "plain",
     "value": "false"
    },
    "Spellcheck": {
     "name": "Spellcheck",
     "mode": "plain",
     "value": "false"
    },
    "Cols": {
     "name": "Cols",
     "mode": "plain",
     "value": false
    },
    "Rows": {
     "name": "Rows",
     "mode": "plain",
     "value": false
    },
    "Value": {
     "name": "Value",
     "mode": "plain",
     "value": ""
    },
    "Wrap": {
     "name": "Wrap",
     "mode": "plain",
     "value": false
    }
   }
  }
 },
 "DateTime": {
  "   7   9   0": {
   "name": "DateTime",
   "properties": {
    "ControlName": {
     "name": "ControlName",
     "mode": "plain",
     "value": ""
    },
    "DoubleBinding": {
     "name": "DoubleBinding",
     "mode": "script",
     "value": false
    },
    "Disabled": {
     "name": "Disabled",
     "mode": "plain",
     "value": "false"
    },
    "IonMode": {
     "name": "IonMode",
     "mode": "plain",
     "value": false
    },
    "CancelText": {
     "name": "CancelText",
     "mode": "plain",
     "value": false
    },
    "DoneText": {
     "name": "DoneText",
     "mode": "plain",
     "value": false
    },
    "DisplayFormat": {
     "name": "DisplayFormat",
     "mode": "plain",
     "value": false
    },
    "DisplayTimeZone": {
     "name": "DisplayTimeZone",
     "mode": "plain",
     "value": false
    },
    "DayNames": {
     "name": "DayNames",
     "mode": "plain",
     "value": false
    },
    "DayShortNames": {
     "name": "DayShortNames",
     "mode": "plain",
     "value": false
    },
    "DayValues": {
     "name": "DayValues",
     "mode": "plain",
     "value": false
    },
    "HourValues": {
     "name": "HourValues",
     "mode": "plain",
     "value": false
    },
    "MonthNames": {
     "name": "MonthNames",
     "mode": "plain",
     "value": false
    },
    "MonthShortNames": {
     "name": "MonthShortNames",
     "mode": "plain",
     "value": false
    },
    "MonthValues": {
     "name": "MonthValues",
     "mode": "plain",
     "value": false
    },
    "MinuteValues": {
     "name": "MinuteValues",
     "mode": "plain",
     "value": false
    },
    "Min": {
     "name": "Min",
     "mode": "plain",
     "value": false
    },
    "Max": {
     "name": "Max",
     "mode": "plain",
     "value": false
    },
    "Placeholder": {
     "name": "Placeholder",
     "mode": "plain",
     "value": false
    },
    "PickerFormat": {
     "name": "PickerFormat",
     "mode": "plain",
     "value": false
    },
    "PickerOptions": {
     "name": "PickerOptions",
     "mode": "plain",
     "value": false
    },
    "Readonly": {
     "name": "Readonly",
     "mode": "plain",
     "value": "false"
    },
    "Value": {
     "name": "Value",
     "mode": "plain",
     "value": false
    },
    "YearValues": {
     "name": "YearValues",
     "mode": "plain",
     "value": false
    }
   }
  }
 },
 "Range": {
  "   7   9   0": {
   "name": "Range",
   "properties": {
    "ControlName": {
     "name": "ControlName",
     "mode": "plain",
     "value": ""
    },
    "DoubleBinding": {
     "name": "DoubleBinding",
     "mode": "script",
     "value": false
    },
    "Disabled": {
     "name": "Disabled",
     "mode": "plain",
     "value": "false"
    },
    "IonColor": {
     "name": "IonColor",
     "mode": "plain",
     "value": false
    },
    "IonMode": {
     "name": "IonMode",
     "mode": "plain",
     "value": false
    },
    "Debounce": {
     "name": "Debounce",
     "mode": "plain",
     "value": "0"
    },
    "DualKnobs": {
     "name": "DualKnobs",
     "mode": "plain",
     "value": "false"
    },
    "Min": {
     "name": "Min",
     "mode": "plain",
     "value": "0"
    },
    "Max": {
     "name": "Max",
     "mode": "plain",
     "value": "100"
    },
    "Pin": {
     "name": "Pin",
     "mode": "plain",
     "value": "false"
    },
    "Snaps": {
     "name": "Snaps",
     "mode": "plain",
     "value": "false"
    },
    "Step": {
     "name": "Step",
     "mode": "plain",
     "value": "1"
    },
    "Ticks": {
     "name": "Ticks",
     "mode": "plain",
     "value": "true"
    },
    "Value": {
     "name": "Value",
     "mode": "plain",
     "value": false
    }
   }
  }
 },
 "Grid": {
  "   7   9   0": {
   "name": "Grid",
   "properties": {
    "Fixed": {
     "name": "Fixed",
     "mode": "plain",
     "value": "false"
    }
   }
  }
 },
 "GridCol": {
  "   7   9   0": {
   "name": "GridCol",
   "properties": {
    "FlexAlignement": {
     "name": "FlexAlignement",
     "mode": "plain",
     "value": false
    },
    "Offset": {
     "name": "Offset",
     "mode": "plain",
     "value": false
    },
    "OffsetLg": {
     "name": "OffsetLg",
     "mode": "plain",
     "value": false
    },
    "OffsetMd": {
     "name": "OffsetMd",
     "mode": "plain",
     "value": false
    },
    "OffsetSm": {
     "name": "OffsetSm",
     "mode": "plain",
     "value": false
    },
    "OffsetXl": {
     "name": "OffsetXl",
     "mode": "plain",
     "value": false
    },
    "OffsetXs": {
     "name": "OffsetXs",
     "mode": "plain",
     "value": false
    },
    "Pull": {
     "name": "Pull",
     "mode": "plain",
     "value": false
    },
    "PullLg": {
     "name": "PullLg",
     "mode": "plain",
     "value": false
    },
    "PullMd": {
     "name": "PullMd",
     "mode": "plain",
     "value": false
    },
    "PullSm": {
     "name": "PullSm",
     "mode": "plain",
     "value": false
    },
    "PullXl": {
     "name": "PullXl",
     "mode": "plain",
     "value": false
    },
    "PullXs": {
     "name": "PullXs",
     "mode": "plain",
     "value": false
    },
    "Push": {
     "name": "Push",
     "mode": "plain",
     "value": false
    },
    "PushLg": {
     "name": "PushLg",
     "mode": "plain",
     "value": false
    },
    "PushMd": {
     "name": "PushMd",
     "mode": "plain",
     "value": false
    },
    "PushSm": {
     "name": "PushSm",
     "mode": "plain",
     "value": false
    },
    "PushXl": {
     "name": "PushXl",
     "mode": "plain",
     "value": false
    },
    "PushXs": {
     "name": "PushXs",
     "mode": "plain",
     "value": false
    },
    "Size": {
     "name": "Size",
     "mode": "plain",
     "value": false
    },
    "SizeLg": {
     "name": "SizeLg",
     "mode": "plain",
     "value": false
    },
    "SizeMd": {
     "name": "SizeMd",
     "mode": "plain",
     "value": false
    },
    "SizeSm": {
     "name": "SizeSm",
     "mode": "plain",
     "value": false
    },
    "SizeXl": {
     "name": "SizeXl",
     "mode": "plain",
     "value": false
    },
    "SizeXs": {
     "name": "SizeXs",
     "mode": "plain",
     "value": false
    }
   }
  }
 },
 "GridRow": {
  "   7   9   0": {
   "name": "GridRow",
   "properties": {
    "FlexJustifyContent": {
     "name": "FlexJustifyContent",
     "mode": "plain",
     "value": false
    },
    "FlexAlignement": {
     "name": "FlexAlignement",
     "mode": "plain",
     "value": false
    },
    "FlexWrap": {
     "name": "FlexWrap",
     "mode": "plain",
     "value": false
    }
   }
  }
 },
 "Card": {
  "   7   9   0": {
   "name": "Card",
   "properties": {
    "Button": {
     "name": "Button",
     "mode": "plain",
     "value": "false"
    },
    "ButtonFormType": {
     "name": "ButtonFormType",
     "mode": "plain",
     "value": "button"
    },
    "Disabled": {
     "name": "Disabled",
     "mode": "plain",
     "value": "false"
    },
    "IonColor": {
     "name": "IonColor",
     "mode": "plain",
     "value": false
    },
    "IonMode": {
     "name": "IonMode",
     "mode": "plain",
     "value": false
    },
    "LinkUrl": {
     "name": "LinkUrl",
     "mode": "plain",
     "value": false
    },
    "LinkDownload": {
     "name": "LinkDownload",
     "mode": "plain",
     "value": false
    },
    "LinkTarget": {
     "name": "LinkTarget",
     "mode": "plain",
     "value": false
    },
    "LinkRel": {
     "name": "LinkRel",
     "mode": "plain",
     "value": false
    },
    "LinkRouterDirection": {
     "name": "LinkRouterDirection",
     "mode": "plain",
     "value": false
    }
   }
  }
 },
 "CardContent": {
  "   7   9   0": {
   "name": "CardContent",
   "properties": {
    "IonMode": {
     "name": "IonMode",
     "mode": "plain",
     "value": false
    }
   }
  }
 },
 "CardHeader": {
  "   7   9   0": {
   "name": "CardHeader",
   "properties": {
    "IonColor": {
     "name": "IonColor",
     "mode": "plain",
     "value": false
    },
    "IonMode": {
     "name": "IonMode",
     "mode": "plain",
     "value": false
    },
    "Translucent": {
     "name": "Translucent",
     "mode": "plain",
     "value": "false"
    }
   }
  }
 },
 "CardSubTitle": {
  "   7   9   0": {
   "name": "CardSubTitle",
   "properties": {
    "IonColor": {
     "name": "IonColor",
     "mode": "plain",
     "value": false
    },
    "IonMode": {
     "name": "IonMode",
     "mode": "plain",
     "value": false
    }
   }
  }
 },
 "CardTitle": {
  "   7   9   0": {
   "name": "CardTitle",
   "properties": {
    "IonColor": {
     "name": "IonColor",
     "mode": "plain",
     "value": false
    },
    "IonMode": {
     "name": "IonMode",
     "mode": "plain",
     "value": false
    }
   }
  }
 }
}