<?xml version="1.0" encoding="UTF-8"?>
<document>
	<object type="object">
		<about type="string">Burt is a Bear.</about>
		<email type="string">burt@example.com</email>
		<id type="string">1_speakers</id>
		<location type="string">Everywhere</location>
		<name type="string">Burt Bear</name>
		<phone type="string">+1-541-754-3010</phone>
		<profilePic type="string">assets/img/speakers/bear.jpg</profilePic>
		<twitter type="string">ionicframework</twitter>
		<att type="object">
			<path type="string">.//data/speakers/bear.jpg</path>
			<name type="string">bear.jpg</name>
		</att>
	</object>
	<object type="object">
		<about type="string">Charlie is a Cheetah.</about>
		<email type="string">charlie@example.com</email>
		<id type="string">2_speakers</id>
		<location type="string">Everywhere</location>
		<name type="string">Charlie Cheetah</name>
		<phone type="string">+1-541-754-3010</phone>
		<profilePic type="string">assets/img/speakers/cheetah.jpg</profilePic>
		<twitter type="string">ionicframework</twitter>
		<att type="object">
			<path type="string">.//data/speakers/cheetah.jpg</path>
			<name type="string">cheetah.jpg</name>
		</att>
	</object>
	<object type="object">
		<about type="string">Donald is a Duck.</about>
		<email type="string">donald@example.com</email>
		<id type="string">3_speakers</id>
		<location type="string">Everywhere</location>
		<name type="string">Donald Duck</name>
		<phone type="string">+1-541-754-3010</phone>
		<profilePic type="string">assets/img/speakers/duck.jpg</profilePic>
		<twitter type="string">ionicframework</twitter>
		<att type="object">
			<path type="string">.//data/speakers/duck.jpg</path>
			<name type="string">duck.jpg</name>
		</att>
	</object>
	<object type="object">
		<about type="string">Eva is an Eagle.</about>
		<email type="string">eva@example.com</email>
		<id type="string">4_speakers</id>
		<location type="string">Everywhere</location>
		<name type="string">Eva Eagle</name>
		<phone type="string">+1-541-754-3010</phone>
		<profilePic type="string">assets/img/speakers/eagle.jpg</profilePic>
		<twitter type="string">ionicframework</twitter>
		<att type="object">
			<path type="string">.//data/speakers/eagle.jpg</path>
			<name type="string">eagle.jpg</name>
		</att>
	</object>
	<object type="object">
		<about type="string">Ellie is an Elephant.</about>
		<email type="string">ellie@example.com</email>
		<id type="string">5_speakers</id>
		<location type="string">Everywhere</location>
		<name type="string">Ellie Elephant</name>
		<phone type="string">+1-541-754-3010</phone>
		<profilePic type="string">assets/img/speakers/elephant.jpg</profilePic>
		<twitter type="string">ionicframework</twitter>
		<att type="object">
			<path type="string">.//data/speakers/elephant.jpg</path>
			<name type="string">elephant.jpg</name>
		</att>
	</object>
	<object type="object">
		<about type="string">Gino is a Giraffe.</about>
		<email type="string">gino@example.com</email>
		<id type="string">6_speakers</id>
		<location type="string">Everywhere</location>
		<name type="string">Gino Giraffe</name>
		<phone type="string">+1-541-754-3010</phone>
		<profilePic type="string">assets/img/speakers/giraffe.jpg</profilePic>
		<twitter type="string">ionicframework</twitter>
		<att type="object">
			<path type="string">.//data/speakers/giraffe.jpg</path>
			<name type="string">giraffe.jpg</name>
		</att>
	</object>
	<object type="object">
		<about type="string">Isabella is an Iguana.</about>
		<email type="string">isabella@example.com</email>
		<id type="string">7_speakers</id>
		<location type="string">Everywhere</location>
		<name type="string">Isabella Iguana</name>
		<phone type="string">+1-541-754-3010</phone>
		<profilePic type="string">assets/img/speakers/iguana.jpg</profilePic>
		<twitter type="string">ionicframework</twitter>
		<att type="object">
			<path type="string">.//data/speakers/iguana.jpg</path>
			<name type="string">iguana.jpg</name>
		</att>
	</object>
	<object type="object">
		<about type="string">Karl is a Kitten.</about>
		<email type="string">karl@example.com</email>
		<id type="string">8_speakers</id>
		<location type="string">Everywhere</location>
		<name type="string">Karl Kitten</name>
		<phone type="string">+1-541-754-3010</phone>
		<profilePic type="string">assets/img/speakers/kitten.jpg</profilePic>
		<twitter type="string">ionicframework</twitter>
		<att type="object">
			<path type="string">.//data/speakers/kitten.jpg</path>
			<name type="string">kitten.jpg</name>
		</att>
	</object>
	<object type="object">
		<about type="string">Lionel is a Lion.</about>
		<email type="string">lionel@example.com</email>
		<id type="string">9_speakers</id>
		<location type="string">Everywhere</location>
		<name type="string">Lionel Lion</name>
		<phone type="string">+1-541-754-3010</phone>
		<profilePic type="string">assets/img/speakers/lion.jpg</profilePic>
		<twitter type="string">ionicframework</twitter>
		<att type="object">
			<path type="string">.//data/speakers/lion.jpg</path>
			<name type="string">lion.jpg</name>
		</att>
	</object>
	<object type="object">
		<about type="string">Molly is a Mouse.</about>
		<email type="string">molly@example.com</email>
		<id type="string">10_speakers</id>
		<location type="string">Everywhere</location>
		<name type="string">Molly Mouse</name>
		<phone type="string">+1-541-754-3010</phone>
		<profilePic type="string">assets/img/speakers/mouse.jpg</profilePic>
		<twitter type="string">ionicframework</twitter>
		<att type="object">
			<path type="string">.//data/speakers/mouse.jpg</path>
			<name type="string">mouse.jpg</name>
		</att>
	</object>
	<object type="object">
		<about type="string">Paul is a Puppy.</about>
		<email type="string">paul@example.com</email>
		<id type="string">11_speakers</id>
		<location type="string">Everywhere</location>
		<name type="string">Paul Puppy</name>
		<phone type="string">+1-541-754-3010</phone>
		<profilePic type="string">assets/img/speakers/puppy.jpg</profilePic>
		<twitter type="string">ionicframework</twitter>
		<att type="object">
			<path type="string">.//data/speakers/puppy.jpg</path>
			<name type="string">puppy.jpg</name>
		</att>
	</object>
	<object type="object">
		<about type="string">Rachel is a Rabbit.</about>
		<email type="string">rachel@example.com</email>
		<id type="string">12_speakers</id>
		<location type="string">Everywhere</location>
		<name type="string">Rachel Rabbit</name>
		<phone type="string">+1-541-754-3010</phone>
		<profilePic type="string">assets/img/speakers/rabbit.jpg</profilePic>
		<twitter type="string">ionicframework</twitter>
		<att type="object">
			<path type="string">.//data/speakers/rabbit.jpg</path>
			<name type="string">rabbit.jpg</name>
		</att>
	</object>
	<object type="object">
		<about type="string">Ted is a Turtle.</about>
		<email type="string">ted@example.com</email>
		<id type="string">13_speakers</id>
		<location type="string">Everywhere</location>
		<name type="string">Ted Turtle</name>
		<phone type="string">+1-541-754-3010</phone>
		<profilePic type="string">assets/img/speakers/turtle.jpg</profilePic>
		<twitter type="string">ionicframework</twitter>
		<att type="object">
			<path type="string">.//data/speakers/turtle.jpg</path>
			<name type="string">turtle.jpg</name>
		</att>
	</object>
</document>