<?xml version="1.0" encoding="UTF-8"?>
<!--
* Copyright (c) 2014 Convertigo. All Rights Reserved.
*
* The copyright to the computer  program(s) herein  is the property
* of Convertigo.
* The program(s) may  be used  and/or copied  only with the written
* permission  of  Convertigo  or in accordance  with  the terms and
* conditions  stipulated  in the agreement/contract under which the
* program(s) have been supplied.
*
* Convertigo makes  no  representations  or  warranties  about  the
* suitability of the software, either express or implied, including
* but  not  limited  to  the implied warranties of merchantability,
* fitness for a particular purpose, or non-infringement. Convertigo
* shall  not  be  liable for  any damage  suffered by licensee as a
* result of using,  modifying or  distributing this software or its
* derivatives.
-->

<!--
 * $URL$
 * $Author$
 * $Revision$
 * $Date$
-->
<completionDictionnary>
	<ctf>
		<entry>
			<keyword>data-c8o-accumulate=""</keyword>
			<definition>Define the accumulation type 'append' or 'prepend'</definition>
		</entry>
		<entry>
			<keyword>data-c8o-after-rendering=""</keyword>
			<definition>Define a method called after the rendering</definition>
		</entry>
		<entry>
			<keyword>data-c8o-before-rendering=""</keyword>
			<definition>Define a method called before the rendering</definition>
		</entry>
		<entry>
			<keyword>data-c8o-call=""</keyword>
			<definition>Call a Convertigo sequence or transaction</definition>
		</entry>
		<entry>
			<keyword>data-c8o-call-condition=""</keyword>
			<definition>Define a conditional call</definition>
		</entry>
		<entry>
			<keyword>data-c8o-call-mode=""</keyword>
			<definition>Call mode to be auto, timer</definition>
		</entry>
		<entry>
			<keyword>data-c8o-each=""</keyword>
			<definition>Iterate on selector for all children</definition>
		</entry>
		<entry>
			<keyword>data-c8o-if=""</keyword>
			<definition>Define a condition</definition>
		</entry>
		<entry>
			<keyword>data-c8o-if-not=""</keyword>
			<definition>Define a negative condition</definition>
		</entry>
		<entry>
			<keyword>data-c8o-late-render=""</keyword>
			<definition>Delay the rendering</definition>
		</entry>
		<entry>
			<keyword>data-c8o-listen=""</keyword>
			<definition>Listen to a Convertigo sequence or transaction</definition>
		</entry>
		<entry>
			<keyword>data-c8o-listen-condition=""</keyword>
			<definition>Define a conditional listener</definition>
		</entry>
		<entry>
			<keyword>data-c8o-ref=""</keyword>
			<definition>Define a reference anchor name</definition>
		</entry>
		<entry>
			<keyword>data-c8o-render=""</keyword>
			<definition>Renders as soon as possible</definition>
		</entry>
		<entry>
			<keyword>data-c8o-use-xxx=""</keyword>
			<definition>Define an attribute for inline templating</definition>
		</entry>
		<entry>
			<keyword>data-c8o-use="on"</keyword>
			<definition>Define an attribute marker for inline templating (on or off)</definition>
		</entry>
		<entry>
			<keyword>data-c8o-variable=""</keyword>
			<definition>Define a variable</definition>
		</entry>
		<entry>
			<keyword>data-c8o-variables=""</keyword>
			<definition>Define several variables</definition>
		</entry>
	</ctf>
	<jquerymobile>
		<entry>
			<keyword>data-corners("true")</keyword>
			<definition></definition>
		</entry>
		<entry>
			<keyword>data-corners("false")</keyword>
			<definition></definition>
		</entry>
		<entry>
			<keyword>data-icon("home")</keyword>
			<definition></definition>
		</entry>
		<entry>
			<keyword>data-icon("delete")</keyword>
			<definition></definition>
		</entry>
		<entry>
			<keyword>data-icon("plus")</keyword>
			<definition></definition>
		</entry>
		<entry>
			<keyword>data-icon("arrow-u")</keyword>
			<definition></definition>
		</entry>
		<entry>
			<keyword>data-icon("arrow-d")</keyword>
			<definition></definition>
		</entry>
		<entry>
			<keyword>data-icon("carat-l")</keyword>
			<definition></definition>
		</entry>
		<entry>
			<keyword>data-icon("carat-t")</keyword>
			<definition></definition>
		</entry>
		<entry>
			<keyword>data-icon("carat-r")</keyword>
			<definition></definition>
		</entry>
		<entry>
			<keyword>data-icon("carat-b")</keyword>
			<definition></definition>
		</entry>
		<entry>
			<keyword>data-icon("check")</keyword>
			<definition></definition>
		</entry>
		<entry>
			<keyword>data-icon("gear")</keyword>
			<definition></definition>
		</entry>
		<entry>
			<keyword>data-icon("grid")</keyword>
			<definition></definition>
		</entry>
		<entry>
			<keyword>data-icon("star")</keyword>
			<definition></definition>
		</entry>
		<entry>
			<keyword>data-icon("custom")</keyword>
			<definition></definition>
		</entry>
		<entry>
			<keyword>data-icon("arrow-r")</keyword>
			<definition></definition>
		</entry>
		<entry>
			<keyword>data-icon("arrow-l")</keyword>
			<definition></definition>
		</entry>
		<entry>
			<keyword>data-icon("minus")</keyword>
			<definition></definition>
		</entry>
		<entry>
			<keyword>data-icon("refresh")</keyword>
			<definition></definition>
		</entry>
		<entry>
			<keyword>data-icon("forward")</keyword>
			<definition></definition>
		</entry>
		<entry>
			<keyword>data-icon("back")</keyword>
			<definition></definition>
		</entry>
		<entry>
			<keyword>data-icon("alert")</keyword>
			<definition></definition>
		</entry>
		<entry>
			<keyword>data-icon("info")</keyword>
			<definition></definition>
		</entry>
		<entry>
			<keyword>data-icon("search")</keyword>
			<definition></definition>
		</entry>
		<entry>
			<keyword>data-iconpos("left")</keyword>
			<definition></definition>
		</entry>
		<entry>
			<keyword>data-iconpos("right")</keyword>
			<definition></definition>
		</entry>
		<entry>
			<keyword>data-iconpos("top")</keyword>
			<definition></definition>
		</entry>
		<entry>
			<keyword>data-iconpos("bottom")</keyword>
			<definition></definition>
		</entry>
		<entry>
			<keyword>data-iconpos("notext")</keyword>
			<definition></definition>
		</entry>
		<entry>
			<keyword>data-iconshadow("true")</keyword>
			<definition></definition>
		</entry>
		<entry>
			<keyword>data-iconshadow("false")</keyword>
			<definition></definition>
		</entry>
		<entry>
			<keyword>data-inline("true")</keyword>
			<definition></definition>
		</entry>
		<entry>
			<keyword>data-inline("false")</keyword>
			<definition></definition>
		</entry>
		<entry>
			<keyword>data-mini("true")</keyword>
			<definition></definition>
		</entry>
		<entry>
			<keyword>data-mini("false - Compact sized version")</keyword>
			<definition></definition>
		</entry>
		<entry>
			<keyword>data-shadow("true")</keyword>
			<definition></definition>
		</entry>
		<entry>
			<keyword>data-shadow("false")</keyword>
			<definition></definition>
		</entry>
		<entry>
			<keyword>data-theme("swatch letter (a-z)")</keyword>
			<definition></definition>
		</entry>
		<entry>
			<keyword>data-mini("true")</keyword>
			<definition></definition>
		</entry>
		<entry>
			<keyword>data-mini("false - Compact sized version")</keyword>
			<definition></definition>
		</entry>
		<entry>
			<keyword>data-role("none - Prevents auto-enhancement to use native control")</keyword>
			<definition></definition>
		</entry>
		<entry>
			<keyword>data-theme("swatch letter (a-z) - Added to the form element")</keyword>
			<definition></definition>
		</entry>
		<entry>
			<keyword>data-collapsed("true")</keyword>
			<definition></definition>
		</entry>
		<entry>
			<keyword>data-collapsed("false")</keyword>
			<definition></definition>
		</entry>
		<entry>
			<keyword>data-collapse-cue-text("string - Text used to provide audible feedback for users with screen reader software. Default: " click to collapse contents"")</keyword>
			<definition></definition>
		</entry>
		<entry>
			<keyword>data-collapsed-icon("home")</keyword>
			<definition></definition>
		</entry>
		<entry>
			<keyword>data-collapsed-icon("delete")</keyword>
			<definition></definition>
		</entry>
		<entry>
			<keyword>data-collapsed-icon("plus")</keyword>
			<definition></definition>
		</entry>
		<entry>
			<keyword>data-collapsed-icon("arrow-u")</keyword>
			<definition></definition>
		</entry>
		<entry>
			<keyword>data-collapsed-icon("arrow-d")</keyword>
			<definition></definition>
		</entry>
		<entry>
			<keyword>data-collapsed-icon("carat-l")</keyword>
			<definition></definition>
		</entry>
		<entry>
			<keyword>data-collapsed-icon("carat-t")</keyword>
			<definition></definition>
		</entry>
		<entry>
			<keyword>data-collapsed-icon("carat-r")</keyword>
			<definition></definition>
		</entry>
		<entry>
			<keyword>data-collapsed-icon("carat-b")</keyword>
			<definition></definition>
		</entry>
		<entry>
			<keyword>data-collapsed-icon("check")</keyword>
			<definition></definition>
		</entry>
		<entry>
			<keyword>data-collapsed-icon("gear")</keyword>
			<definition></definition>
		</entry>
		<entry>
			<keyword>data-collapsed-icon("grid")</keyword>
			<definition></definition>
		</entry>
		<entry>
			<keyword>data-collapsed-icon("star")</keyword>
			<definition></definition>
		</entry>
		<entry>
			<keyword>data-collapsed-icon("custom")</keyword>
			<definition></definition>
		</entry>
		<entry>
			<keyword>data-collapsed-icon("arrow-r")</keyword>
			<definition></definition>
		</entry>
		<entry>
			<keyword>data-collapsed-icon("arrow-l")</keyword>
			<definition></definition>
		</entry>
		<entry>
			<keyword>data-collapsed-icon("minus")</keyword>
			<definition></definition>
		</entry>
		<entry>
			<keyword>data-collapsed-icon("refresh")</keyword>
			<definition></definition>
		</entry>
		<entry>
			<keyword>data-collapsed-icon("forward")</keyword>
			<definition></definition>
		</entry>
		<entry>
			<keyword>data-collapsed-icon("back")</keyword>
			<definition></definition>
		</entry>
		<entry>
			<keyword>data-collapsed-icon("alert")</keyword>
			<definition></definition>
		</entry>
		<entry>
			<keyword>data-collapsed-icon("info")</keyword>
			<definition></definition>
		</entry>
		<entry>
			<keyword>data-collapsed-icon("search")</keyword>
			<definition></definition>
		</entry>
		<entry>
			<keyword>data-collapsed-icon("false")</keyword>
			<definition></definition>
		</entry>
		<entry>
			<keyword>data-content-theme("swatch letter (a-z)")</keyword>
			<definition></definition>
		</entry>
		<entry>
			<keyword>data-expand-cue-text("string - Text used to provide audible feedback for users with screen reader software. Default: " click to expand contents"")</keyword>
			<definition></definition>
		</entry>
		<entry>
			<keyword>data-expanded-icon("home")</keyword>
			<definition></definition>
		</entry>
		<entry>
			<keyword>data-expanded-icon("delete")</keyword>
			<definition></definition>
		</entry>
		<entry>
			<keyword>data-expanded-icon("plus")</keyword>
			<definition></definition>
		</entry>
		<entry>
			<keyword>data-expanded-icon("arrow-u")</keyword>
			<definition></definition>
		</entry>
		<entry>
			<keyword>data-expanded-icon("arrow-d")</keyword>
			<definition></definition>
		</entry>
		<entry>
			<keyword>data-expanded-icon("carat-l")</keyword>
			<definition></definition>
		</entry>
		<entry>
			<keyword>data-expanded-icon("carat-t")</keyword>
			<definition></definition>
		</entry>
		<entry>
			<keyword>data-expanded-icon("carat-r")</keyword>
			<definition></definition>
		</entry>
		<entry>
			<keyword>data-expanded-icon("carat-b| check")</keyword>
			<definition></definition>
		</entry>
		<entry>
			<keyword>data-expanded-icon("gear")</keyword>
			<definition></definition>
		</entry>
		<entry>
			<keyword>data-expanded-icon("grid")</keyword>
			<definition></definition>
		</entry>
		<entry>
			<keyword>data-expanded-icon("star")</keyword>
			<definition></definition>
		</entry>
		<entry>
			<keyword>data-expanded-icon("custom")</keyword>
			<definition></definition>
		</entry>
		<entry>
			<keyword>data-expanded-icon("arrow-r")</keyword>
			<definition></definition>
		</entry>
		<entry>
			<keyword>data-expanded-icon("arrow-l")</keyword>
			<definition></definition>
		</entry>
		<entry>
			<keyword>data-expanded-icon("minus")</keyword>
			<definition></definition>
		</entry>
		<entry>
			<keyword>data-expanded-icon("refresh")</keyword>
			<definition></definition>
		</entry>
		<entry>
			<keyword>data-expanded-icon("forward")</keyword>
			<definition></definition>
		</entry>
		<entry>
			<keyword>data-expanded-icon("back")</keyword>
			<definition></definition>
		</entry>
		<entry>
			<keyword>data-expanded-icon("alert")</keyword>
			<definition></definition>
		</entry>
		<entry>
			<keyword>data-expanded-icon("info")</keyword>
			<definition></definition>
		</entry>
		<entry>
			<keyword>data-expanded-icon("search")</keyword>
			<definition></definition>
		</entry>
		<entry>
			<keyword>data-iconpos("left")</keyword>
			<definition></definition>
		</entry>
		<entry>
			<keyword>data-iconpos("right")</keyword>
			<definition></definition>
		</entry>
		<entry>
			<keyword>data-iconpos("top")</keyword>
			<definition></definition>
		</entry>
		<entry>
			<keyword>data-iconpos("bottom")</keyword>
			<definition></definition>
		</entry>
		<entry>
			<keyword>data-inset("true")</keyword>
			<definition></definition>
		</entry>
		<entry>
			<keyword>data-inset("false")</keyword>
			<definition></definition>
		</entry>
		<entry>
			<keyword>data-mini("true")</keyword>
			<definition></definition>
		</entry>
		<entry>
			<keyword>data-mini("false - Compact sized version")</keyword>
			<definition></definition>
		</entry>
		<entry>
			<keyword>data-theme("swatch letter (a-z)")</keyword>
			<definition></definition>
		</entry>
		<entry>
			<keyword>data-collapsed-icon("home")</keyword>
			<definition></definition>
		</entry>
		<entry>
			<keyword>data-collapsed-icon("delete")</keyword>
			<definition></definition>
		</entry>
		<entry>
			<keyword>data-collapsed-icon("plus")</keyword>
			<definition></definition>
		</entry>
		<entry>
			<keyword>data-collapsed-icon("arrow-u")</keyword>
			<definition></definition>
		</entry>
		<entry>
			<keyword>data-collapsed-icon("arrow-d")</keyword>
			<definition></definition>
		</entry>
		<entry>
			<keyword>data-collapsed-icon("carat-l")</keyword>
			<definition></definition>
		</entry>
		<entry>
			<keyword>data-collapsed-icon("carat-t")</keyword>
			<definition></definition>
		</entry>
		<entry>
			<keyword>data-collapsed-icon("carat-r")</keyword>
			<definition></definition>
		</entry>
		<entry>
			<keyword>data-collapsed-icon("carat-b| check")</keyword>
			<definition></definition>
		</entry>
		<entry>
			<keyword>data-collapsed-icon("gear")</keyword>
			<definition></definition>
		</entry>
		<entry>
			<keyword>data-collapsed-icon("grid")</keyword>
			<definition></definition>
		</entry>
		<entry>
			<keyword>data-collapsed-icon("star")</keyword>
			<definition></definition>
		</entry>
		<entry>
			<keyword>data-collapsed-icon("custom")</keyword>
			<definition></definition>
		</entry>
		<entry>
			<keyword>data-collapsed-icon("arrow-r")</keyword>
			<definition></definition>
		</entry>
		<entry>
			<keyword>data-collapsed-icon("arrow-l")</keyword>
			<definition></definition>
		</entry>
		<entry>
			<keyword>data-collapsed-icon("minus")</keyword>
			<definition></definition>
		</entry>
		<entry>
			<keyword>data-collapsed-icon("refresh")</keyword>
			<definition></definition>
		</entry>
		<entry>
			<keyword>data-collapsed-icon("forward")</keyword>
			<definition></definition>
		</entry>
		<entry>
			<keyword>data-collapsed-icon("back")</keyword>
			<definition></definition>
		</entry>
		<entry>
			<keyword>data-collapsed-icon("alert")</keyword>
			<definition></definition>
		</entry>
		<entry>
			<keyword>data-collapsed-icon("info")</keyword>
			<definition></definition>
		</entry>
		<entry>
			<keyword>data-collapsed-icon("search")</keyword>
			<definition></definition>
		</entry>
		<entry>
			<keyword>data-content-theme("swatch letter (a-z) - Sets all collapsibles in set")</keyword>
			<definition></definition>
		</entry>
		<entry>
			<keyword>data-expanded-icon("home")</keyword>
			<definition></definition>
		</entry>
		<entry>
			<keyword>data-expanded-icon("delete")</keyword>
			<definition></definition>
		</entry>
		<entry>
			<keyword>data-expanded-icon("plus")</keyword>
			<definition></definition>
		</entry>
		<entry>
			<keyword>data-expanded-icon("arrow-u")</keyword>
			<definition></definition>
		</entry>
		<entry>
			<keyword>data-expanded-icon("arrow-d")</keyword>
			<definition></definition>
		</entry>
		<entry>
			<keyword>data-expanded-icon("carat-l")</keyword>
			<definition></definition>
		</entry>
		<entry>
			<keyword>data-expanded-icon("carat-t")</keyword>
			<definition></definition>
		</entry>
		<entry>
			<keyword>data-expanded-icon("carat-r")</keyword>
			<definition></definition>
		</entry>
		<entry>
			<keyword>data-expanded-icon("carat-b| check")</keyword>
			<definition></definition>
		</entry>
		<entry>
			<keyword>data-expanded-icon("gear")</keyword>
			<definition></definition>
		</entry>
		<entry>
			<keyword>data-expanded-icon("grid")</keyword>
			<definition></definition>
		</entry>
		<entry>
			<keyword>data-expanded-icon("star")</keyword>
			<definition></definition>
		</entry>
		<entry>
			<keyword>data-expanded-icon("custom")</keyword>
			<definition></definition>
		</entry>
		<entry>
			<keyword>data-expanded-icon("arrow-r")</keyword>
			<definition></definition>
		</entry>
		<entry>
			<keyword>data-expanded-icon("arrow-l")</keyword>
			<definition></definition>
		</entry>
		<entry>
			<keyword>data-expanded-icon("minus")</keyword>
			<definition></definition>
		</entry>
		<entry>
			<keyword>data-expanded-icon("refresh")</keyword>
			<definition></definition>
		</entry>
		<entry>
			<keyword>data-expanded-icon("forward")</keyword>
			<definition></definition>
		</entry>
		<entry>
			<keyword>data-expanded-icon("back")</keyword>
			<definition></definition>
		</entry>
		<entry>
			<keyword>data-expanded-icon("alert")</keyword>
			<definition></definition>
		</entry>
		<entry>
			<keyword>data-expanded-icon("info")</keyword>
			<definition></definition>
		</entry>
		<entry>
			<keyword>data-expanded-icon("search")</keyword>
			<definition></definition>
		</entry>
		<entry>
			<keyword>data-iconpos("left")</keyword>
			<definition></definition>
		</entry>
		<entry>
			<keyword>data-iconpos("right")</keyword>
			<definition></definition>
		</entry>
		<entry>
			<keyword>data-iconpos("top")</keyword>
			<definition></definition>
		</entry>
		<entry>
			<keyword>data-iconpos("bottom")</keyword>
			<definition></definition>
		</entry>
		<entry>
			<keyword>data-iconpos(" notext")</keyword>
			<definition></definition>
		</entry>
		<entry>
			<keyword>data-inset("true")</keyword>
			<definition></definition>
		</entry>
		<entry>
			<keyword>data-inset("false")</keyword>
			<definition></definition>
		</entry>
		<entry>
			<keyword>data-mini("true")</keyword>
			<definition></definition>
		</entry>
		<entry>
			<keyword>data-mini("false - Compact sized version")</keyword>
			<definition></definition>
		</entry>
		<entry>
			<keyword>data-theme("swatch letter (a-z) - Sets all collapsibles in set")</keyword>
			<definition></definition>
		</entry>
		<entry>
			<keyword>data-exclude-invisible("true")</keyword>
			<definition></definition>
		</entry>
		<entry>
			<keyword>data-exclude-invisible("false - Sets whether to exclude invisible children in the assignment of rounded corners")</keyword>
			<definition></definition>
		</entry>
		<entry>
			<keyword>data-mini("true")</keyword>
			<definition></definition>
		</entry>
		<entry>
			<keyword>data-mini("false - Compact sized version for all items in the controlgroup")</keyword>
			<definition></definition>
		</entry>
		<entry>
			<keyword>data-theme("swatch letter (a-z)")</keyword>
			<definition></definition>
		</entry>
		<entry>
			<keyword>data-type("horizontal")</keyword>
			<definition></definition>
		</entry>
		<entry>
			<keyword>data-type("vertical - For horizontal or vertical item alignment")</keyword>
			<definition></definition>
		</entry>
		<entry>
			<keyword>data-close-btn("left")</keyword>
			<definition></definition>
		</entry>
		<entry>
			<keyword>data-close-btn("right")</keyword>
			<definition></definition>
		</entry>
		<entry>
			<keyword>data-close-btn("none")</keyword>
			<definition></definition>
		</entry>
		<entry>
			<keyword>data-close-btn-text("string - Text for the close button, dialog only. Default: "close"")</keyword>
			<definition></definition>
		</entry>
		<entry>
			<keyword>data-corners("true")</keyword>
			<definition></definition>
		</entry>
		<entry>
			<keyword>data-corners("false")</keyword>
			<definition></definition>
		</entry>
		<entry>
			<keyword>data-dom-cache("true")</keyword>
			<definition></definition>
		</entry>
		<entry>
			<keyword>data-dom-cache("false")</keyword>
			<definition></definition>
		</entry>
		<entry>
			<keyword>data-overlay-theme("swatch letter (a-z) - Overlay theme when the page is opened in a dialog")</keyword>
			<definition></definition>
		</entry>
		<entry>
			<keyword>data-theme("swatch letter (a-z)")</keyword>
			<definition></definition>
		</entry>
		<entry>
			<keyword>data-title("string - Title used when page is shown")</keyword>
			<definition></definition>
		</entry>
		<entry>
			<keyword>data-enhance("true")</keyword>
			<definition></definition>
		</entry>
		<entry>
			<keyword>data-enhance("false")</keyword>
			<definition></definition>
		</entry>
		<entry>
			<keyword>data-ajax("true")</keyword>
			<definition></definition>
		</entry>
		<entry>
			<keyword>data-ajax("false")</keyword>
			<definition></definition>
		</entry>
		<entry>
			<keyword>data-mini("true")</keyword>
			<definition></definition>
		</entry>
		<entry>
			<keyword>data-mini("false - Compact sized version")</keyword>
			<definition></definition>
		</entry>
		<entry>
			<keyword>data-role("none - Prevents auto-enhancement to use native control")</keyword>
			<definition></definition>
		</entry>
		<entry>
			<keyword>data-theme("swatch letter (a-z) - Added to the form element")</keyword>
			<definition></definition>
		</entry>
		<entry>
			<keyword>data-track-theme("swatch letter (a-z) - Added to the form element")</keyword>
			<definition></definition>
		</entry>
		<entry>
			<keyword>data-autodividers("true")</keyword>
			<definition></definition>
		</entry>
		<entry>
			<keyword>data-autodividers("false")</keyword>
			<definition></definition>
		</entry>
		<entry>
			<keyword>data-count-theme("swatch letter (a-z) - Default "c"")</keyword>
			<definition></definition>
		</entry>
		<entry>
			<keyword>data-divider-theme("swatch letter (a-z) - Default "b"")</keyword>
			<definition></definition>
		</entry>
		<entry>
			<keyword>data-filter("true")</keyword>
			<definition></definition>
		</entry>
		<entry>
			<keyword>data-filter("false")</keyword>
			<definition></definition>
		</entry>
		<entry>
			<keyword>data-filter-placeholder("string")</keyword>
			<definition></definition>
		</entry>
		<entry>
			<keyword>data-filter-theme("swatch letter (a-z)")</keyword>
			<definition></definition>
		</entry>
		<entry>
			<keyword>data-header-theme("swatch letter (a-z)")</keyword>
			<definition></definition>
		</entry>
		<entry>
			<keyword>data-icon("home")</keyword>
			<definition></definition>
		</entry>
		<entry>
			<keyword>data-icon("delete")</keyword>
			<definition></definition>
		</entry>
		<entry>
			<keyword>data-icon("plus")</keyword>
			<definition></definition>
		</entry>
		<entry>
			<keyword>data-icon("arrow-u")</keyword>
			<definition></definition>
		</entry>
		<entry>
			<keyword>data-icon("arrow-d")</keyword>
			<definition></definition>
		</entry>
		<entry>
			<keyword>data-icon("carat-l")</keyword>
			<definition></definition>
		</entry>
		<entry>
			<keyword>data-icon("carat-t")</keyword>
			<definition></definition>
		</entry>
		<entry>
			<keyword>data-icon("carat-r")</keyword>
			<definition></definition>
		</entry>
		<entry>
			<keyword>data-icon("carat-b| check")</keyword>
			<definition></definition>
		</entry>
		<entry>
			<keyword>data-icon("gear")</keyword>
			<definition></definition>
		</entry>
		<entry>
			<keyword>data-icon("grid")</keyword>
			<definition></definition>
		</entry>
		<entry>
			<keyword>data-icon("star")</keyword>
			<definition></definition>
		</entry>
		<entry>
			<keyword>data-icon("custom")</keyword>
			<definition></definition>
		</entry>
		<entry>
			<keyword>data-icon("arrow-r")</keyword>
			<definition></definition>
		</entry>
		<entry>
			<keyword>data-icon("arrow-l")</keyword>
			<definition></definition>
		</entry>
		<entry>
			<keyword>data-icon("minus")</keyword>
			<definition></definition>
		</entry>
		<entry>
			<keyword>data-icon("refresh")</keyword>
			<definition></definition>
		</entry>
		<entry>
			<keyword>data-icon("forward")</keyword>
			<definition></definition>
		</entry>
		<entry>
			<keyword>data-icon("back")</keyword>
			<definition></definition>
		</entry>
		<entry>
			<keyword>data-icon("alert")</keyword>
			<definition></definition>
		</entry>
		<entry>
			<keyword>data-icon("info")</keyword>
			<definition></definition>
		</entry>
		<entry>
			<keyword>data-icon("search")</keyword>
			<definition></definition>
		</entry>
		<entry>
			<keyword>data-icon("false")</keyword>
			<definition></definition>
		</entry>
		<entry>
			<keyword>data-inset("true")</keyword>
			<definition></definition>
		</entry>
		<entry>
			<keyword>data-inset("false")</keyword>
			<definition></definition>
		</entry>
		<entry>
			<keyword>data-split-icon("home")</keyword>
			<definition></definition>
		</entry>
		<entry>
			<keyword>data-split-icon("delete")</keyword>
			<definition></definition>
		</entry>
		<entry>
			<keyword>data-split-icon("plus")</keyword>
			<definition></definition>
		</entry>
		<entry>
			<keyword>data-split-icon("arrow-u")</keyword>
			<definition></definition>
		</entry>
		<entry>
			<keyword>data-split-icon("arrow-d")</keyword>
			<definition></definition>
		</entry>
		<entry>
			<keyword>data-split-icon("carat-l")</keyword>
			<definition></definition>
		</entry>
		<entry>
			<keyword>data-split-icon("carat-t")</keyword>
			<definition></definition>
		</entry>
		<entry>
			<keyword>data-split-icon("carat-r")</keyword>
			<definition></definition>
		</entry>
		<entry>
			<keyword>data-split-icon("carat-b| check")</keyword>
			<definition></definition>
		</entry>
		<entry>
			<keyword>data-split-icon("gear")</keyword>
			<definition></definition>
		</entry>
		<entry>
			<keyword>data-split-icon("grid")</keyword>
			<definition></definition>
		</entry>
		<entry>
			<keyword>data-split-icon("star")</keyword>
			<definition></definition>
		</entry>
		<entry>
			<keyword>data-split-icon("custom")</keyword>
			<definition></definition>
		</entry>
		<entry>
			<keyword>data-split-icon("arrow-r")</keyword>
			<definition></definition>
		</entry>
		<entry>
			<keyword>data-split-icon("arrow-l")</keyword>
			<definition></definition>
		</entry>
		<entry>
			<keyword>data-split-icon("minus")</keyword>
			<definition></definition>
		</entry>
		<entry>
			<keyword>data-split-icon("refresh")</keyword>
			<definition></definition>
		</entry>
		<entry>
			<keyword>data-split-icon("forward")</keyword>
			<definition></definition>
		</entry>
		<entry>
			<keyword>data-split-icon("back")</keyword>
			<definition></definition>
		</entry>
		<entry>
			<keyword>data-split-icon("alert")</keyword>
			<definition></definition>
		</entry>
		<entry>
			<keyword>data-split-icon("info")</keyword>
			<definition></definition>
		</entry>
		<entry>
			<keyword>data-split-icon("search")</keyword>
			<definition></definition>
		</entry>
		<entry>
			<keyword>data-split-theme("swatch letter (a-z) - Default "b"")</keyword>
			<definition></definition>
		</entry>
		<entry>
			<keyword>data-theme("swatch letter (a-z)")</keyword>
			<definition></definition>
		</entry>
		<entry>
			<keyword>data-filtertext("string - Filter by this value instead of inner text")</keyword>
			<definition></definition>
		</entry>
		<entry>
			<keyword>data-icon("home")</keyword>
			<definition></definition>
		</entry>
		<entry>
			<keyword>data-icon("delete")</keyword>
			<definition></definition>
		</entry>
		<entry>
			<keyword>data-icon("plus")</keyword>
			<definition></definition>
		</entry>
		<entry>
			<keyword>data-icon("arrow-u")</keyword>
			<definition></definition>
		</entry>
		<entry>
			<keyword>data-icon("arrow-d")</keyword>
			<definition></definition>
		</entry>
		<entry>
			<keyword>data-icon("carat-l")</keyword>
			<definition></definition>
		</entry>
		<entry>
			<keyword>data-icon("carat-t")</keyword>
			<definition></definition>
		</entry>
		<entry>
			<keyword>data-icon("carat-r")</keyword>
			<definition></definition>
		</entry>
		<entry>
			<keyword>data-icon("carat-b| check")</keyword>
			<definition></definition>
		</entry>
		<entry>
			<keyword>data-icon("gear")</keyword>
			<definition></definition>
		</entry>
		<entry>
			<keyword>data-icon("grid")</keyword>
			<definition></definition>
		</entry>
		<entry>
			<keyword>data-icon("star")</keyword>
			<definition></definition>
		</entry>
		<entry>
			<keyword>data-icon("custom")</keyword>
			<definition></definition>
		</entry>
		<entry>
			<keyword>data-icon("arrow-r")</keyword>
			<definition></definition>
		</entry>
		<entry>
			<keyword>data-icon("arrow-l")</keyword>
			<definition></definition>
		</entry>
		<entry>
			<keyword>data-icon("minus")</keyword>
			<definition></definition>
		</entry>
		<entry>
			<keyword>data-icon("refresh")</keyword>
			<definition></definition>
		</entry>
		<entry>
			<keyword>data-icon("forward")</keyword>
			<definition></definition>
		</entry>
		<entry>
			<keyword>data-icon("back")</keyword>
			<definition></definition>
		</entry>
		<entry>
			<keyword>data-icon("alert")</keyword>
			<definition></definition>
		</entry>
		<entry>
			<keyword>data-icon("info")</keyword>
			<definition></definition>
		</entry>
		<entry>
			<keyword>data-icon("search")</keyword>
			<definition></definition>
		</entry>
		<entry>
			<keyword>data-icon("false")</keyword>
			<definition></definition>
		</entry>
		<entry>
			<keyword>data-role("list-divider")</keyword>
			<definition></definition>
		</entry>
		<entry>
			<keyword>data-theme("swatch letter (a-z)")</keyword>
			<definition></definition>
		</entry>
		<entry>
			<keyword>data-iconpos("left")</keyword>
			<definition></definition>
		</entry>
		<entry>
			<keyword>data-iconpos("right")</keyword>
			<definition></definition>
		</entry>
		<entry>
			<keyword>data-iconpos("top")</keyword>
			<definition></definition>
		</entry>
		<entry>
			<keyword>data-iconpos("bottom")</keyword>
			<definition></definition>
		</entry>
		<entry>
			<keyword>data-iconpos(" notext")</keyword>
			<definition></definition>
		</entry>
		<entry>
			<keyword>data-dom-cache("true")</keyword>
			<definition></definition>
		</entry>
		<entry>
			<keyword>data-dom-cache("false")</keyword>
			<definition></definition>
		</entry>
		<entry>
			<keyword>data-overlay-theme("swatch letter (a-z) - Overlay theme when the page is opened as a dialog")</keyword>
			<definition></definition>
		</entry>
		<entry>
			<keyword>data-theme("swatch letter (a-z) - Default "a"")</keyword>
			<definition></definition>
		</entry>
		<entry>
			<keyword>data-title("string - Title used when page is shown")</keyword>
			<definition></definition>
		</entry>
		<entry>
			<keyword>data-url("url - Value for updating the URL, instead of the url used to request the page")</keyword>
			<definition></definition>
		</entry>
		<entry>
			<keyword>data-corners("true")</keyword>
			<definition></definition>
		</entry>
		<entry>
			<keyword>data-corners("false")</keyword>
			<definition></definition>
		</entry>
		<entry>
			<keyword>data-dismissible("true")</keyword>
			<definition></definition>
		</entry>
		<entry>
			<keyword>data-dismissible("false - If set to false prevents popup closing by clicking outside of the popup or pressing the Escape key")</keyword>
			<definition></definition>
		</entry>
		<entry>
			<keyword>data-history("true")</keyword>
			<definition></definition>
		</entry>
		<entry>
			<keyword>data-history("false - Sets whether the popup creates a browser history item when it opens. If set to false, it will not create a history item, and will thus not be closeable via the browser's "Back" button.")</keyword>
			<definition></definition>
		</entry>
		<entry>
			<keyword>data-overlay-theme("swatch letter (a-z) - Default "null" (transparent background)")</keyword>
			<definition></definition>
		</entry>
		<entry>
			<keyword>data-position-to("origin")</keyword>
			<definition></definition>
		</entry>
		<entry>
			<keyword>data-position-to("window")</keyword>
			<definition></definition>
		</entry>
		<entry>
			<keyword>data-position-to("selector - "origin" indicates that the popup is to be centered over the link that opens it. "window" indicates that it is to be centered in the browser window. If you give a jQuery selector, it will be centered over the first element returned by the selector, if that element is visible. Otherwise, it will be centered in the browser window.")</keyword>
			<definition></definition>
		</entry>
		<entry>
			<keyword>data-shadow("true")</keyword>
			<definition></definition>
		</entry>
		<entry>
			<keyword>data-shadow("false")</keyword>
			<definition></definition>
		</entry>
		<entry>
			<keyword>data-theme("swatch letter (a-z)")</keyword>
			<definition></definition>
		</entry>
		<entry>
			<keyword>data-theme("none - Default inherited, "none" sets the popup to transparent")</keyword>
			<definition></definition>
		</entry>
		<entry>
			<keyword>data-tolerance("30,15,30,15 - Distance from the edges of the window (top, right, bottom, left)")</keyword>
			<definition></definition>
		</entry>
		<entry>
			<keyword>data-transition("none")</keyword>
			<definition></definition>
		</entry>
		<entry>
			<keyword>data-transition("transition - The transition to use when making the popup appear/disappear.")</keyword>
			<definition></definition>
		</entry>
		<entry>
			<keyword>data-mini("true")</keyword>
			<definition></definition>
		</entry>
		<entry>
			<keyword>data-mini("false - Compact sized version")</keyword>
			<definition></definition>
		</entry>
		<entry>
			<keyword>data-role("none - Prevents auto-enhancement to use native control")</keyword>
			<definition></definition>
		</entry>
		<entry>
			<keyword>data-theme("swatch letter (a-z) - Added to the form element")</keyword>
			<definition></definition>
		</entry>
		<entry>
			<keyword>data-divider-theme("swatch letter (a-z) - Default "b" - Only applicable if optgroup support is used in non-native selects")</keyword>
			<definition></definition>
		</entry>
		<entry>
			<keyword>data-icon("home")</keyword>
			<definition></definition>
		</entry>
		<entry>
			<keyword>data-icon("delete")</keyword>
			<definition></definition>
		</entry>
		<entry>
			<keyword>data-icon("plus")</keyword>
			<definition></definition>
		</entry>
		<entry>
			<keyword>data-icon("arrow-u")</keyword>
			<definition></definition>
		</entry>
		<entry>
			<keyword>data-icon("arrow-d")</keyword>
			<definition></definition>
		</entry>
		<entry>
			<keyword>data-icon("carat-l")</keyword>
			<definition></definition>
		</entry>
		<entry>
			<keyword>data-icon("carat-t")</keyword>
			<definition></definition>
		</entry>
		<entry>
			<keyword>data-icon("carat-r")</keyword>
			<definition></definition>
		</entry>
		<entry>
			<keyword>data-icon("carat-b")</keyword>
			<definition></definition>
		</entry>
		<entry>
			<keyword>data-icon("check")</keyword>
			<definition></definition>
		</entry>
		<entry>
			<keyword>data-icon("gear")</keyword>
			<definition></definition>
		</entry>
		<entry>
			<keyword>data-icon("grid")</keyword>
			<definition></definition>
		</entry>
		<entry>
			<keyword>data-icon("star")</keyword>
			<definition></definition>
		</entry>
		<entry>
			<keyword>data-icon("custom")</keyword>
			<definition></definition>
		</entry>
		<entry>
			<keyword>data-icon("arrow-r")</keyword>
			<definition></definition>
		</entry>
		<entry>
			<keyword>data-icon("arrow-l")</keyword>
			<definition></definition>
		</entry>
		<entry>
			<keyword>data-icon("minus")</keyword>
			<definition></definition>
		</entry>
		<entry>
			<keyword>data-icon("refresh")</keyword>
			<definition></definition>
		</entry>
		<entry>
			<keyword>data-icon("forward")</keyword>
			<definition></definition>
		</entry>
		<entry>
			<keyword>data-icon("back")</keyword>
			<definition></definition>
		</entry>
		<entry>
			<keyword>data-icon("alert")</keyword>
			<definition></definition>
		</entry>
		<entry>
			<keyword>data-icon("info")</keyword>
			<definition></definition>
		</entry>
		<entry>
			<keyword>data-icon("search")</keyword>
			<definition></definition>
		</entry>
		<entry>
			<keyword>data-icon("false ")</keyword>
			<definition></definition>
		</entry>
		<entry>
			<keyword>data-iconpos("left")</keyword>
			<definition></definition>
		</entry>
		<entry>
			<keyword>data-iconpos("right")</keyword>
			<definition></definition>
		</entry>
		<entry>
			<keyword>data-iconpos("top")</keyword>
			<definition></definition>
		</entry>
		<entry>
			<keyword>data-iconpos("bottom")</keyword>
			<definition></definition>
		</entry>
		<entry>
			<keyword>data-iconpos(" notext")</keyword>
			<definition></definition>
		</entry>
		<entry>
			<keyword>data-inline("true")</keyword>
			<definition></definition>
		</entry>
		<entry>
			<keyword>data-inline("false")</keyword>
			<definition></definition>
		</entry>
		<entry>
			<keyword>data-mini("true")</keyword>
			<definition></definition>
		</entry>
		<entry>
			<keyword>data-mini("false - Compact sized version")</keyword>
			<definition></definition>
		</entry>
		<entry>
			<keyword>data-native-menu("true")</keyword>
			<definition></definition>
		</entry>
		<entry>
			<keyword>data-native-menu("false")</keyword>
			<definition></definition>
		</entry>
		<entry>
			<keyword>data-overlay-theme("swatch letter (a-z) - Overlay theme for non-native selects")</keyword>
			<definition></definition>
		</entry>
		<entry>
			<keyword>data-placeholder("true")</keyword>
			<definition></definition>
		</entry>
		<entry>
			<keyword>data-placeholder("false - Can be set on option element of a non-native select")</keyword>
			<definition></definition>
		</entry>
		<entry>
			<keyword>data-role("none - Prevents auto-enhancement to use native control")</keyword>
			<definition></definition>
		</entry>
		<entry>
			<keyword>data-theme("swatch letter (a-z) - Added to the form element")</keyword>
			<definition></definition>
		</entry>
		<entry>
			<keyword>data-highlight("true")</keyword>
			<definition></definition>
		</entry>
		<entry>
			<keyword>data-highlight("false - Adds an active state fill on track to handle")</keyword>
			<definition></definition>
		</entry>
		<entry>
			<keyword>data-mini("true")</keyword>
			<definition></definition>
		</entry>
		<entry>
			<keyword>data-mini("false - Compact sized version")</keyword>
			<definition></definition>
		</entry>
		<entry>
			<keyword>data-role("none - Prevents auto-enhancement to use native control")</keyword>
			<definition></definition>
		</entry>
		<entry>
			<keyword>data-theme("swatch letter (a-z) - Added to the form element")</keyword>
			<definition></definition>
		</entry>
		<entry>
			<keyword>data-track-theme("swatch letter (a-z) - Added to the form element")</keyword>
			<definition></definition>
		</entry>
		<entry>
			<keyword>data-clear-btn("true")</keyword>
			<definition></definition>
		</entry>
		<entry>
			<keyword>data-clear-btn("false - Adds a clear button")</keyword>
			<definition></definition>
		</entry>
		<entry>
			<keyword>data-clear-btn-text("string - Text for the close button. Default: "clear text"")</keyword>
			<definition></definition>
		</entry>
		<entry>
			<keyword>data-mini("true")</keyword>
			<definition></definition>
		</entry>
		<entry>
			<keyword>data-mini("false - Compact sized version")</keyword>
			<definition></definition>
		</entry>
		<entry>
			<keyword>data-role("none - Prevents auto-enhancement to use native control")</keyword>
			<definition></definition>
		</entry>
		<entry>
			<keyword>data-theme("swatch letter (a-z) - Added to the form element")</keyword>
			<definition></definition>
		</entry>
		<entry>
			<keyword>data-add-back-btn("true")</keyword>
			<definition></definition>
		</entry>
		<entry>
			<keyword>data-add-back-btn("false - Auto add back button, header only")</keyword>
			<definition></definition>
		</entry>
		<entry>
			<keyword>data-back-btn-text("string - Header only")</keyword>
			<definition></definition>
		</entry>
		<entry>
			<keyword>data-back-btn-theme("A")</keyword>
			<definition></definition>
		</entry>
		<entry>
			<keyword>data-id("string - Unique ID. Required for persistent footers")</keyword>
			<definition></definition>
		</entry>
		<entry>
			<keyword>data-position("fixed")</keyword>
			<definition></definition>
		</entry>
		<entry>
			<keyword>data-theme("swatch letter (a-z)")</keyword>
			<definition></definition>
		</entry>
		<entry>
			<keyword>data-disable-page-zoom("true")</keyword>
			<definition></definition>
		</entry>
		<entry>
			<keyword>data-disable-page-zoom("false - User-scaling-ability for pages with fixed toolbars")</keyword>
			<definition></definition>
		</entry>
		<entry>
			<keyword>data-fullscreen("true")</keyword>
			<definition></definition>
		</entry>
		<entry>
			<keyword>data-fullscreen("false - Setting toolbars over the page-content")</keyword>
			<definition></definition>
		</entry>
		<entry>
			<keyword>data-tap-toggle("true")</keyword>
			<definition></definition>
		</entry>
		<entry>
			<keyword>data-tap-toggle("false - Ability to toggle toolbar-visibility on user tap/click")</keyword>
			<definition></definition>
		</entry>
		<entry>
			<keyword>data-transition("slide")</keyword>
			<definition></definition>
		</entry>
		<entry>
			<keyword>data-transition("fade")</keyword>
			<definition></definition>
		</entry>
		<entry>
			<keyword>data-transition("none - Show/hide-transition when a tap/click occurs")</keyword>
			<definition></definition>
		</entry>
		<entry>
			<keyword>data-update-page-padding("true")</keyword>
			<definition></definition>
		</entry>
		<entry>
			<keyword>data-update-page-padding("false - Have the page top and bottom padding updated on resize, transition, "updatelayout" events (the framework always updates the padding on the "pageshow" event).")</keyword>
			<definition></definition>
		</entry>
		<entry>
			<keyword>data-visible-on-page-show("true")</keyword>
			<definition></definition>
		</entry>
		<entry>
			<keyword>data-visible-on-page-show("false - Toolbar-visibility when parent page is shown")</keyword>
			<definition></definition>
		</entry>	
	</jquerymobile>
</completionDictionnary>
